Classfile /E:/vopen/service/target/classes/com/msxf/vopen/service/biz/impl/jd/JDApplyServiceImpl.class
  Last modified 26-Sep-2017; size 27232 bytes
  MD5 checksum d45e04e5d88be1d3218d427f94c92d1f
  Compiled from "JDApplyServiceImpl.java"
public class com.msxf.vopen.service.biz.impl.jd.JDApplyServiceImpl implements com.msxf.vopen.service.biz.jd.JDApplyService
  minor version: 0
  major version: 51
  flags: ACC_PUBLIC, ACC_SUPER
Constant pool:
     #1 = Class              #619         // com/msxf/vopen/util/jd/JDCommonUtil
     #2 = Methodref          #7.#620      // java/lang/Object."<init>":()V
     #3 = Methodref          #621.#622    // com/msxf/vopen/dto/jd/CommonRequest.getRequestData:()Ljava/lang/String;
     #4 = Class              #623         // com/msxf/vopen/dto/req/jd/CheckApplyReqDTO
     #5 = Methodref          #624.#625    // com/alibaba/fastjson/JSONObject.parseObject:(Ljava/lang/String;Ljava/lang/Class;)Ljava/lang/Object;
     #6 = String             #626         // 统计各合作方提交申请次数
     #7 = Class              #627         // java/lang/Object
     #8 = String             #628         // 授信申请来自合作方
     #9 = String             #629         // jd
    #10 = Methodref          #630.#631    // com/msxf/boot/core/util/log/BusinessLogger.log:(Ljava/lang/String;[Ljava/lang/Object;)V
    #11 = Methodref          #4.#632      // com/msxf/vopen/dto/req/jd/CheckApplyReqDTO.getUserInfo:()Lcom/msxf/vopen/dto/req/jd/CheckApplyReqDTO$UserInfoDTO;
    #12 = Fieldref           #388.#633    // com/msxf/vopen/service/biz/impl/jd/JDApplyServiceImpl.bizHelpService:Lcom/msxf/vopen/service/biz/BizHelpService;
    #13 = InterfaceMethodref #634.#635    // com/msxf/vopen/service/biz/BizHelpService.getApiCaller:(Ljava/lang/String;)Lcom/msxf/vopen/support/ApiCaller;
    #14 = Fieldref           #388.#636    // com/msxf/vopen/service/biz/impl/jd/JDApplyServiceImpl.appBaseService:Lcom/msxf/vopen/service/AppBaseService;
    #15 = Methodref          #637.#638    // com/msxf/vopen/service/AppBaseService.getChannelInfo:(Ljava/lang/String;)Lcom/msxf/vopen/entity/ChannelEntity;
    #16 = String             #639         //
    #17 = Fieldref           #388.#640    // com/msxf/vopen/service/biz/impl/jd/JDApplyServiceImpl.jdUserDao:Lcom/msxf/vopen/repository/ThirdRelationRepository;
    #18 = Methodref          #4.#641      // com/msxf/vopen/dto/req/jd/CheckApplyReqDTO.getApplyNo:()Ljava/lang/String;
    #19 = InterfaceMethodref #642.#643    // com/msxf/vopen/repository/ThirdRelationRepository.findByThirdApplyNo:(Ljava/lang/String;Ljava/lang/String;)Lcom/msxf/vopen/entity/ThirdRelationEntity;
    #20 = Fieldref           #388.#644    // com/msxf/vopen/service/biz/impl/jd/JDApplyServiceImpl.iApplicationService:Lcom/msxf/uds/uas/sdk/IApplicationService;
    #21 = InterfaceMethodref #645.#641    // com/msxf/uds/uas/sdk/IApplicationService.getApplyNo:()Ljava/lang/String;
    #22 = Methodref          #486.#646    // com/msxf/vopen/dto/req/jd/CheckApplyReqDTO$UserInfoDTO.getUserId:()Ljava/lang/String;
    #23 = Methodref          #388.#647    // com/msxf/vopen/service/biz/impl/jd/JDApplyServiceImpl.uploadJDUserOCRInfo:(Ljava/lang/String;Ljava/lang/String;)V
    #24 = Class              #648         // java/lang/Exception
    #25 = Fieldref           #388.#649    // com/msxf/vopen/service/biz/impl/jd/JDApplyServiceImpl.logger:Lorg/slf4j/Logger;
    #26 = String             #650         // 京东OCR用户信息拉取上传异常：[{}]
    #27 = Methodref          #24.#651     // java/lang/Exception.getMessage:()Ljava/lang/String;
    #28 = InterfaceMethodref #652.#653    // org/slf4j/Logger.warn:(Ljava/lang/String;Ljava/lang/Object;Ljava/lang/Object;)V
    #29 = Class              #654         // com/msxf/vopen/dto/jd/CommonResponse
    #30 = Fieldref           #655.#656    // com/msxf/vopen/constants/JDRespCodeEnum.UNKNOWN_ERROR:Lcom/msxf/vopen/constants/JDRespCodeEnum;
    #31 = String             #657         // OCR拉取/上传异常
    #32 = Methodref          #29.#658     // com/msxf/vopen/dto/jd/CommonResponse."<init>":(Lcom/msxf/vopen/constants/JDRespCodeEnum;Ljava/lang/String;)V
    #33 = Fieldref           #388.#659    // com/msxf/vopen/service/biz/impl/jd/JDApplyServiceImpl.bizUserService:Lcom/msxf/vopen/service/biz/BizUserService;
    #34 = Methodref          #388.#660    // com/msxf/vopen/service/biz/impl/jd/JDApplyServiceImpl.getAuthCodeReqParams:(Lcom/msxf/vopen/dto/req/jd/CheckApplyReqDTO$UserInfoDTO;)Lcom/msxf/vopen/dto/req/CreditAuthCodeReqDTO;
    #35 = InterfaceMethodref #661.#662    // com/msxf/vopen/service/biz/BizUserService.getCreditAuthCode:(Lcom/msxf/vopen/dto/req/CreditAuthCodeReqDTO;)Lcom/msxf/vopen/constants/CommonResult;
    #36 = Methodref          #663.#664    // com/msxf/vopen/constants/CommonResult.getCode:()I
    #37 = Methodref          #665.#666    // com/alibaba/fastjson/JSON.toJSONString:(Ljava/lang/Object;)Ljava/lang/String;
    #38 = String             #667         // 京东异常:获取征信授权码异常:{},请求参数:[{}]
    #39 = Methodref          #663.#651    // com/msxf/vopen/constants/CommonResult.getMessage:()Ljava/lang/String;
    #40 = Methodref          #663.#668    // com/msxf/vopen/constants/CommonResult.getData:()Ljava/lang/Object;
    #41 = Class              #669         // com/msxf/vopen/dto/resp/CreditAuthCodeRespDTO
    #42 = Methodref          #41.#670     // com/msxf/vopen/dto/resp/CreditAuthCodeRespDTO.getAuthCode:()Ljava/lang/String;
    #43 = Fieldref           #388.#671    // com/msxf/vopen/service/biz/impl/jd/JDApplyServiceImpl.dscService:Lcom/msxf/eyas/dsc/DSCService;
    #44 = Methodref          #486.#672    // com/msxf/vopen/dto/req/jd/CheckApplyReqDTO$UserInfoDTO.getUsername:()Ljava/lang/String;
    #45 = Methodref          #486.#673    // com/msxf/vopen/dto/req/jd/CheckApplyReqDTO$UserInfoDTO.getCertNo:()Ljava/lang/String;
    #46 = InterfaceMethodref #674.#675    // com/msxf/eyas/dsc/DSCService.getUniqueId:(Ljava/lang/String;Ljava/lang/String;)Ljava/lang/String;
    #47 = Fieldref           #388.#676    // com/msxf/vopen/service/biz/impl/jd/JDApplyServiceImpl.userInfoQueryService:Lcom/msxf/eyas/cmc/sdk/user/IUserInfoQueryService;
    #48 = Methodref          #486.#677    // com/msxf/vopen/dto/req/jd/CheckApplyReqDTO$UserInfoDTO.getUserTel:()Ljava/lang/String;
    #49 = InterfaceMethodref #678.#679    // com/msxf/eyas/cmc/sdk/user/IUserInfoQueryService.getBaseUserInfoByMobile:(Ljava/lang/String;)Lcom/msxf/eyas/cmc/vo/user/UserBaseInfoVO;
    #50 = Methodref          #388.#680    // com/msxf/vopen/service/biz/impl/jd/JDApplyServiceImpl.mobileRegParams:(Lcom/msxf/vopen/dto/req/jd/CheckApplyReqDTO$UserInfoDTO;Lcom/msxf/vopen/support/ApiCaller;)Lcom/msxf/eyas/cmc/vo/user/UserMobileRegVo;
    #51 = Fieldref           #388.#681    // com/msxf/vopen/service/biz/impl/jd/JDApplyServiceImpl.cmcUserService:Lcom/msxf/eyas/cmc/sdk/user/IUserService;
    #52 = InterfaceMethodref #682.#683    // com/msxf/eyas/cmc/sdk/user/IUserService.mobileReg:(Lcom/msxf/eyas/cmc/vo/user/UserMobileRegVo;)Lcom/msxf/eyas/cmc/vo/user/LoginResultVO;
    #53 = Class              #684         // com/msxf/eyas/cmc/CMCException
    #54 = String             #685         // 京东异常:手机号注册异常:{},手机号:{}
    #55 = Methodref          #53.#651     // com/msxf/eyas/cmc/CMCException.getMessage:()Ljava/lang/String;
    #56 = Methodref          #240.#686    // com/msxf/eyas/cmc/vo/user/UserMobileRegVo.getMobile:()Ljava/lang/String;
    #57 = Methodref          #388.#687    // com/msxf/vopen/service/biz/impl/jd/JDApplyServiceImpl.createCustParams:(Lcom/msxf/vopen/dto/req/jd/CheckApplyReqDTO;Ljava/lang/String;)Lcom/msxf/eyas/cmc/vo/cust/CustInfoVO;
    #58 = Fieldref           #388.#688    // com/msxf/vopen/service/biz/impl/jd/JDApplyServiceImpl.iCustInfoService:Lcom/msxf/eyas/cmc/sdk/cust/ICustInfoService;
    #59 = InterfaceMethodref #689.#690    // com/msxf/eyas/cmc/sdk/cust/ICustInfoService.createCust:(Lcom/msxf/eyas/cmc/vo/cust/CustInfoVO;)Lcom/msxf/eyas/cmc/vo/user/UserBaseInfoVO;
    #60 = String             #691         // 京东异常:创建客户异常:{},UUID:{}
    #61 = Methodref          #296.#692    // com/msxf/eyas/cmc/vo/cust/CustInfoVO.getUniqueId:()Ljava/lang/String;
    #62 = Fieldref           #388.#693    // com/msxf/vopen/service/biz/impl/jd/JDApplyServiceImpl.bizNotifyService:Lcom/msxf/vopen/service/biz/BizNotifyService;
    #63 = Methodref          #694.#695    // com/msxf/eyas/cmc/vo/user/LoginResultVO.getUserId:()Ljava/lang/Long;
    #64 = Methodref          #696.#697    // com/msxf/vopen/entity/ChannelEntity.getCode:()Ljava/lang/String;
    #65 = Methodref          #696.#698    // com/msxf/vopen/entity/ChannelEntity.getYouqianTerminal:()Ljava/lang/String;
    #66 = Methodref          #696.#699    // com/msxf/vopen/entity/ChannelEntity.getYouqianChannel:()Ljava/lang/String;
    #67 = InterfaceMethodref #700.#701    // com/msxf/vopen/service/biz/BizNotifyService.notifyYouqianUserRecommendedInfo:(Ljava/lang/Long;Ljava/lang/String;Ljava/lang/String;Ljava/lang/String;)V
    #68 = Methodref          #702.#703    // com/msxf/eyas/cmc/vo/user/UserBaseInfoVO.getId:()Ljava/lang/Long;
    #69 = Methodref          #621.#704    // com/msxf/vopen/dto/jd/CommonRequest.getRequestNo:()Ljava/lang/String;
    #70 = Methodref          #388.#705    // com/msxf/vopen/service/biz/impl/jd/JDApplyServiceImpl.getApplyVo:(Lcom/msxf/vopen/dto/req/jd/CheckApplyReqDTO;Ljava/lang/String;Lcom/msxf/vopen/support/ApiCaller;Ljava/lang/String;Ljava/lang/String;Ljava/lang/String;Ljava/lang/Long;)Lcom/msxf/uds/uas/sdk/vo/ApplyVo;
    #71 = InterfaceMethodref #645.#706    // com/msxf/uds/uas/sdk/IApplicationService.apply:(Lcom/msxf/uds/uas/sdk/vo/ApplyVo;)Ljava/lang/String;
    #72 = Class              #707         // com/msxf/uds/uas/exception/UASException
    #73 = String             #708         // 京东异常:提交申请单异常:{},申请单号:{}
    #74 = Methodref          #72.#651     // com/msxf/uds/uas/exception/UASException.getMessage:()Ljava/lang/String;
    #75 = Fieldref           #709.#710    // com/msxf/uds/uas/exception/UASErrorCode.APPLY_QUERY_SIGN_ORDER:Lcom/msxf/uds/uas/exception/UASErrorCode;
    #76 = Methodref          #709.#697    // com/msxf/uds/uas/exception/UASErrorCode.getCode:()Ljava/lang/String;
    #77 = Methodref          #72.#711     // com/msxf/uds/uas/exception/UASException.getErrorCode:()Ljava/lang/String;
    #78 = Methodref          #253.#712    // java/lang/String.equals:(Ljava/lang/Object;)Z
    #79 = Fieldref           #655.#713    // com/msxf/vopen/constants/JDRespCodeEnum.APPLY_QUERY_SIGN_ORDER:Lcom/msxf/vopen/constants/JDRespCodeEnum;
    #80 = Methodref          #29.#714     // com/msxf/vopen/dto/jd/CommonResponse."<init>":(Lcom/msxf/vopen/dto/jd/CommonRequest;Lcom/msxf/vopen/constants/JDRespCodeEnum;)V
    #81 = Methodref          #388.#715    // com/msxf/vopen/service/biz/impl/jd/JDApplyServiceImpl.saveJDUserInfo:(Lcom/msxf/vopen/dto/req/jd/CheckApplyReqDTO;Ljava/lang/String;Ljava/lang/String;)Lcom/msxf/vopen/entity/ThirdRelationEntity;
    #82 = InterfaceMethodref #642.#716    // com/msxf/vopen/repository/ThirdRelationRepository.save:(Ljava/lang/Object;)Ljava/lang/Object;
    #83 = Class              #717         // com/msxf/uds/uas/sdk/vo/ApplyQueryRequestVo
    #84 = Methodref          #83.#620     // com/msxf/uds/uas/sdk/vo/ApplyQueryRequestVo."<init>":()V
    #85 = Methodref          #83.#718     // com/msxf/uds/uas/sdk/vo/ApplyQueryRequestVo.setApplyNo:(Ljava/lang/String;)V
    #86 = InterfaceMethodref #645.#719    // com/msxf/uds/uas/sdk/IApplicationService.getApplyDetail:(Lcom/msxf/uds/uas/sdk/vo/ApplyQueryRequestVo;)Lcom/msxf/uds/uas/sdk/vo/ApplyQueryDetailVo;
    #87 = Fieldref           #388.#720    // com/msxf/vopen/service/biz/impl/jd/JDApplyServiceImpl.jdNotifyService:Lcom/msxf/vopen/service/biz/jd/JDNotifyService;
    #88 = InterfaceMethodref #721.#722    // com/msxf/vopen/service/biz/jd/JDNotifyService.syncNotifyDataPlatformRiskInfo:(Lcom/msxf/vopen/dto/jd/CommonRequest;)V
    #89 = Fieldref           #388.#723    // com/msxf/vopen/service/biz/impl/jd/JDApplyServiceImpl.commonUtil:Lcom/msxf/vopen/util/jd/JDCommonUtil;
    #90 = Methodref          #724.#725    // com/msxf/uds/uas/sdk/vo/ApplyQueryDetailVo.getAgreementTariffRate:()Ljava/lang/String;
    #91 = Methodref          #1.#726      // com/msxf/vopen/util/jd/JDCommonUtil.parseJdSvcfee:(Ljava/lang/String;)Ljava/lang/String;
    #92 = Methodref          #326.#641    // com/msxf/vopen/entity/ThirdRelationEntity.getApplyNo:()Ljava/lang/String;
    #93 = Fieldref           #388.#727    // com/msxf/vopen/service/biz/impl/jd/JDApplyServiceImpl.redis:Lredis/clients/jedis/JedisCluster;
    #94 = Class              #728         // com/msxf/vopen/constants/RedisConstants
    #95 = String             #729         // vopen_jd_notify_apply
    #96 = Fieldref           #94.#730     // com/msxf/vopen/constants/RedisConstants.EXPIRE_7DAY:Ljava/lang/Integer;
    #97 = Methodref          #731.#732    // java/lang/Integer.intValue:()I
    #98 = Methodref          #4.#733      // com/msxf/vopen/dto/req/jd/CheckApplyReqDTO.getNotifyUrl:()Ljava/lang/String;
    #99 = Methodref          #734.#735    // redis/clients/jedis/JedisCluster.setex:(Ljava/lang/String;ILjava/lang/String;)Ljava/lang/String;
   #100 = Fieldref           #655.#736    // com/msxf/vopen/constants/JDRespCodeEnum.SUCCESS:Lcom/msxf/vopen/constants/JDRespCodeEnum;
   #101 = Methodref          #388.#737    // com/msxf/vopen/service/biz/impl/jd/JDApplyServiceImpl.jdResp:(Ljava/lang/String;Lcom/msxf/vopen/dto/req/jd/CheckApplyReqDTO;Ljava/lang/String;)Lcom/msxf/vopen/dto/resp/jd/CheckApplyRespDTO;
   #102 = Methodref          #29.#738     // com/msxf/vopen/dto/jd/CommonResponse."<init>":(Lcom/msxf/vopen/dto/jd/CommonRequest;Lcom/msxf/vopen/constants/JDRespCodeEnum;Ljava/lang/String;)V
   #103 = Class              #739         // com/msxf/vopen/dto/resp/jd/CheckApplyRespDTO
   #104 = Methodref          #103.#620    // com/msxf/vopen/dto/resp/jd/CheckApplyRespDTO."<init>":()V
   #105 = Methodref          #103.#740    // com/msxf/vopen/dto/resp/jd/CheckApplyRespDTO.setMhtApplyNo:(Ljava/lang/String;)V
   #106 = Methodref          #103.#718    // com/msxf/vopen/dto/resp/jd/CheckApplyRespDTO.setApplyNo:(Ljava/lang/String;)V
   #107 = Methodref          #724.#741    // com/msxf/uds/uas/sdk/vo/ApplyQueryDetailVo.getStatus:()Ljava/lang/String;
   #108 = Methodref          #1.#742      // com/msxf/vopen/util/jd/JDCommonUtil.parseJDApplyStatus:(Ljava/lang/String;)Ljava/lang/String;
   #109 = Methodref          #103.#743    // com/msxf/vopen/dto/resp/jd/CheckApplyRespDTO.setCheckStatus:(Ljava/lang/String;)V
   #110 = Methodref          #724.#744    // com/msxf/uds/uas/sdk/vo/ApplyQueryDetailVo.getAccLmt:()Ljava/math/BigDecimal;
   #111 = Methodref          #1.#745      // com/msxf/vopen/util/jd/JDCommonUtil.parseCent:(Ljava/math/BigDecimal;)Ljava/lang/String;
   #112 = Methodref          #103.#746    // com/msxf/vopen/dto/resp/jd/CheckApplyRespDTO.setCheckAmount:(Ljava/lang/String;)V
   #113 = Methodref          #724.#747    // com/msxf/uds/uas/sdk/vo/ApplyQueryDetailVo.getApplyTime:()Ljava/util/Date;
   #114 = Methodref          #1.#748      // com/msxf/vopen/util/jd/JDCommonUtil.formatJdDate:(Ljava/util/Date;)Ljava/lang/String;
   #115 = Methodref          #103.#749    // com/msxf/vopen/dto/resp/jd/CheckApplyRespDTO.setCheckTime:(Ljava/lang/String;)V
   #116 = Methodref          #4.#750      // com/msxf/vopen/dto/req/jd/CheckApplyReqDTO.getApplyProduct:()Ljava/lang/String;
   #117 = Methodref          #388.#751    // com/msxf/vopen/service/biz/impl/jd/JDApplyServiceImpl.getProductInfo:(Ljava/lang/String;Ljava/lang/String;)Lcom/msxf/vopen/dto/resp/jd/CheckApplyRespDTO$ProductInfoDTO;
   #118 = Methodref          #103.#752    // com/msxf/vopen/dto/resp/jd/CheckApplyRespDTO.setProductInfo:(Lcom/msxf/vopen/dto/resp/jd/CheckApplyRespDTO$ProductInfoDTO;)V
   #119 = Methodref          #753.#754    // org/apache/commons/lang3/time/DateUtils.addDays:(Ljava/util/Date;I)Ljava/util/Date;
   #120 = Methodref          #103.#755    // com/msxf/vopen/dto/resp/jd/CheckApplyRespDTO.setExpiryTime:(Ljava/lang/String;)V
   #121 = Class              #756         // com/msxf/vopen/dto/resp/jd/CheckApplyRespDTO$ProductInfoDTO
   #122 = Methodref          #121.#620    // com/msxf/vopen/dto/resp/jd/CheckApplyRespDTO$ProductInfoDTO."<init>":()V
   #123 = Methodref          #121.#757    // com/msxf/vopen/dto/resp/jd/CheckApplyRespDTO$ProductInfoDTO.setProductId:(Ljava/lang/String;)V
   #124 = Class              #758         // com/msxf/vopen/constants/JDConstants
   #125 = String             #759         // 0.000483
   #126 = Methodref          #121.#760    // com/msxf/vopen/dto/resp/jd/CheckApplyRespDTO$ProductInfoDTO.setInterestRate:(Ljava/lang/String;)V
   #127 = String             #761         // 3,6,9,12
   #128 = Methodref          #121.#762    // com/msxf/vopen/dto/resp/jd/CheckApplyRespDTO$ProductInfoDTO.setSupportPeriod:(Ljava/lang/String;)V
   #129 = String             #763         // 0
   #130 = Methodref          #121.#764    // com/msxf/vopen/dto/resp/jd/CheckApplyRespDTO$ProductInfoDTO.setEarlyRepayment:(Ljava/lang/String;)V
   #131 = String             #765         // EQUAL_PRINCIPAL_INTEREST
   #132 = Methodref          #121.#766    // com/msxf/vopen/dto/resp/jd/CheckApplyRespDTO$ProductInfoDTO.setRepaymentMethod:(Ljava/lang/String;)V
   #133 = String             #767         // 1
   #134 = Methodref          #121.#768    // com/msxf/vopen/dto/resp/jd/CheckApplyRespDTO$ProductInfoDTO.setPartialWithdraw:(Ljava/lang/String;)V
   #135 = String             #769         // MONTHLY_SAVINGS
   #136 = Methodref          #121.#770    // com/msxf/vopen/dto/resp/jd/CheckApplyRespDTO$ProductInfoDTO.setInterestsCalculation:(Ljava/lang/String;)V
   #137 = String             #771         // 0.003
   #138 = Methodref          #121.#772    // com/msxf/vopen/dto/resp/jd/CheckApplyRespDTO$ProductInfoDTO.setOverdueInterestRate:(Ljava/lang/String;)V
   #139 = Class              #773         // java/lang/StringBuilder
   #140 = Methodref          #139.#620    // java/lang/StringBuilder."<init>":()V
   #141 = String             #774         // 服务费率
   #142 = Methodref          #139.#775    // java/lang/StringBuilder.append:(Ljava/lang/String;)Ljava/lang/StringBuilder;
   #143 = String             #776         // %/月
   #144 = Methodref          #139.#777    // java/lang/StringBuilder.toString:()Ljava/lang/String;
   #145 = Methodref          #121.#778    // com/msxf/vopen/dto/resp/jd/CheckApplyRespDTO$ProductInfoDTO.setFeeDesc:(Ljava/lang/String;)V
   #146 = Class              #779         // com/msxf/uds/uas/sdk/vo/ApplyVo
   #147 = Methodref          #146.#620    // com/msxf/uds/uas/sdk/vo/ApplyVo."<init>":()V
   #148 = Methodref          #146.#780    // com/msxf/uds/uas/sdk/vo/ApplyVo.setUserId:(Ljava/lang/Long;)V
   #149 = Methodref          #146.#718    // com/msxf/uds/uas/sdk/vo/ApplyVo.setApplyNo:(Ljava/lang/String;)V
   #150 = Methodref          #146.#781    // com/msxf/uds/uas/sdk/vo/ApplyVo.setApplySerialNo:(Ljava/lang/String;)V
   #151 = Methodref          #146.#782    // com/msxf/uds/uas/sdk/vo/ApplyVo.setUniqueId:(Ljava/lang/String;)V
   #152 = String             #783         // 5208
   #153 = Methodref          #146.#784    // com/msxf/uds/uas/sdk/vo/ApplyVo.setProductCode:(Ljava/lang/String;)V
   #154 = Class              #785         // com/msxf/vopen/constants/Constants
   #155 = String             #786         // VOPEN
   #156 = Methodref          #146.#787    // com/msxf/uds/uas/sdk/vo/ApplyVo.setSubTerminalType:(Ljava/lang/String;)V
   #157 = Methodref          #788.#789    // com/msxf/vopen/support/ApiCaller.getApplication:()Lcom/msxf/vopen/support/ApiApplication;
   #158 = Methodref          #790.#791    // com/msxf/vopen/support/ApiApplication.getCooperator:()Ljava/lang/String;
   #159 = Methodref          #146.#792    // com/msxf/uds/uas/sdk/vo/ApplyVo.setCooperatorId:(Ljava/lang/String;)V
   #160 = String             #793         // PL18
   #161 = Methodref          #146.#794    // com/msxf/uds/uas/sdk/vo/ApplyVo.setLoanPurpose:(Ljava/lang/String;)V
   #162 = Fieldref           #795.#796    // com/msxf/eyas/enums/LifeInsurancePlan.NO:Lcom/msxf/eyas/enums/LifeInsurancePlan;
   #163 = Methodref          #795.#797    // com/msxf/eyas/enums/LifeInsurancePlan.getStandardValue:()Ljava/lang/String;
   #164 = Methodref          #146.#798    // com/msxf/uds/uas/sdk/vo/ApplyVo.setJoinLifeInsurance:(Ljava/lang/String;)V
   #165 = Fieldref           #799.#800    // com/msxf/vopen/constants/PrepayPkgEnum.NO:Lcom/msxf/vopen/constants/PrepayPkgEnum;
   #166 = Methodref          #799.#697    // com/msxf/vopen/constants/PrepayPkgEnum.getCode:()Ljava/lang/String;
   #167 = Methodref          #146.#801    // com/msxf/uds/uas/sdk/vo/ApplyVo.setPrepayPkgInd:(Ljava/lang/String;)V
   #168 = Methodref          #146.#802    // com/msxf/uds/uas/sdk/vo/ApplyVo.setName:(Ljava/lang/String;)V
   #169 = Methodref          #803.#804    // com/msxf/vopen/util/StringUtil.getGender:(Ljava/lang/String;)Ljava/lang/String;
   #170 = Methodref          #146.#805    // com/msxf/uds/uas/sdk/vo/ApplyVo.setGender:(Ljava/lang/String;)V
   #171 = Methodref          #803.#806    // com/msxf/vopen/util/StringUtil.getBirth:(Ljava/lang/String;)Ljava/util/Date;
   #172 = Methodref          #146.#807    // com/msxf/uds/uas/sdk/vo/ApplyVo.setBirth:(Ljava/util/Date;)V
   #173 = Methodref          #146.#808    // com/msxf/uds/uas/sdk/vo/ApplyVo.setIdNo:(Ljava/lang/String;)V
   #174 = Methodref          #146.#809    // com/msxf/uds/uas/sdk/vo/ApplyVo.setCellphone:(Ljava/lang/String;)V
   #175 = String             #810         // 6222368888888888888
   #176 = Methodref          #146.#811    // com/msxf/uds/uas/sdk/vo/ApplyVo.setBankCardNo:(Ljava/lang/String;)V
   #177 = String             #812         // default@msxf.com
   #178 = Methodref          #146.#813    // com/msxf/uds/uas/sdk/vo/ApplyVo.setEmail:(Ljava/lang/String;)V
   #179 = String             #814         // Y
   #180 = Methodref          #146.#815    // com/msxf/uds/uas/sdk/vo/ApplyVo.setEmpPost:(Ljava/lang/String;)V
   #181 = String             #816         // Z
   #182 = Methodref          #146.#817    // com/msxf/uds/uas/sdk/vo/ApplyVo.setEmpType:(Ljava/lang/String;)V
   #183 = Methodref          #146.#818    // com/msxf/uds/uas/sdk/vo/ApplyVo.setEmpStructure:(Ljava/lang/String;)V
   #184 = Fieldref           #154.#819    // com/msxf/vopen/constants/Constants.DEFAULT_MONTH_INCOME:Ljava/lang/Long;
   #185 = Methodref          #146.#820    // com/msxf/uds/uas/sdk/vo/ApplyVo.setMonthIncome:(Ljava/lang/Long;)V
   #186 = Methodref          #486.#821    // com/msxf/vopen/dto/req/jd/CheckApplyReqDTO$UserInfoDTO.getHomeAddressProvince:()Ljava/lang/String;
   #187 = Methodref          #146.#822    // com/msxf/uds/uas/sdk/vo/ApplyVo.setAbodeStateName:(Ljava/lang/String;)V
   #188 = Methodref          #486.#823    // com/msxf/vopen/dto/req/jd/CheckApplyReqDTO$UserInfoDTO.getHomeAddressCity:()Ljava/lang/String;
   #189 = Methodref          #146.#824    // com/msxf/uds/uas/sdk/vo/ApplyVo.setAbodeCityName:(Ljava/lang/String;)V
   #190 = Methodref          #486.#825    // com/msxf/vopen/dto/req/jd/CheckApplyReqDTO$UserInfoDTO.getHomeAddressArea:()Ljava/lang/String;
   #191 = Methodref          #146.#826    // com/msxf/uds/uas/sdk/vo/ApplyVo.setAbodeZoneName:(Ljava/lang/String;)V
   #192 = Methodref          #486.#827    // com/msxf/vopen/dto/req/jd/CheckApplyReqDTO$UserInfoDTO.getHomeAddressDetail:()Ljava/lang/String;
   #193 = Methodref          #146.#828    // com/msxf/uds/uas/sdk/vo/ApplyVo.setAbodeDetail:(Ljava/lang/String;)V
   #194 = Methodref          #146.#829    // com/msxf/uds/uas/sdk/vo/ApplyVo.setCreditAuthSerialNo:(Ljava/lang/String;)V
   #195 = String             #830         // 中国银行
   #196 = Methodref          #146.#831    // com/msxf/uds/uas/sdk/vo/ApplyVo.setBankName:(Ljava/lang/String;)V
   #197 = String             #832         // 北京市
   #198 = Methodref          #146.#833    // com/msxf/uds/uas/sdk/vo/ApplyVo.setBankCityName:(Ljava/lang/String;)V
   #199 = Methodref          #146.#834    // com/msxf/uds/uas/sdk/vo/ApplyVo.setBankProvinceName:(Ljava/lang/String;)V
   #200 = Methodref          #4.#835      // com/msxf/vopen/dto/req/jd/CheckApplyReqDTO.getApplyAmount:()Ljava/lang/String;
   #201 = Methodref          #836.#837    // org/apache/commons/lang3/StringUtils.isEmpty:(Ljava/lang/CharSequence;)Z
   #202 = Methodref          #1.#838      // com/msxf/vopen/util/jd/JDCommonUtil.parseYuan:(Ljava/lang/String;)Ljava/math/BigDecimal;
   #203 = Methodref          #146.#839    // com/msxf/uds/uas/sdk/vo/ApplyVo.setApplyLmt:(Ljava/math/BigDecimal;)V
   #204 = Methodref          #4.#840      // com/msxf/vopen/dto/req/jd/CheckApplyReqDTO.getApplyPeriod:()Ljava/lang/String;
   #205 = Methodref          #731.#841    // java/lang/Integer.valueOf:(Ljava/lang/String;)Ljava/lang/Integer;
   #206 = Methodref          #146.#842    // com/msxf/uds/uas/sdk/vo/ApplyVo.setApplyLoanTerm:(Ljava/lang/Integer;)V
   #207 = Class              #843         // java/util/ArrayList
   #208 = Methodref          #207.#620    // java/util/ArrayList."<init>":()V
   #209 = Methodref          #486.#844    // com/msxf/vopen/dto/req/jd/CheckApplyReqDTO$UserInfoDTO.getEmergList:()Ljava/util/List;
   #210 = InterfaceMethodref #845.#846    // java/util/List.iterator:()Ljava/util/Iterator;
   #211 = InterfaceMethodref #847.#848    // java/util/Iterator.hasNext:()Z
   #212 = InterfaceMethodref #847.#849    // java/util/Iterator.next:()Ljava/lang/Object;
   #213 = Class              #850         // com/msxf/vopen/dto/req/jd/CheckApplyReqDTO$UserInfoDTO$emergInfoDTO
   #214 = Class              #851         // com/msxf/uds/uas/sdk/vo/ApplyCustContactVo
   #215 = Methodref          #214.#620    // com/msxf/uds/uas/sdk/vo/ApplyCustContactVo."<init>":()V
   #216 = Methodref          #213.#852    // com/msxf/vopen/dto/req/jd/CheckApplyReqDTO$UserInfoDTO$emergInfoDTO.getEmergName:()Ljava/lang/String;
   #217 = Methodref          #214.#853    // com/msxf/uds/uas/sdk/vo/ApplyCustContactVo.setContactName:(Ljava/lang/String;)V
   #218 = Methodref          #213.#854    // com/msxf/vopen/dto/req/jd/CheckApplyReqDTO$UserInfoDTO$emergInfoDTO.getEmergRelation:()Ljava/lang/String;
   #219 = Methodref          #388.#855    // com/msxf/vopen/service/biz/impl/jd/JDApplyServiceImpl.parseContactRelation:(Ljava/lang/String;)Ljava/lang/String;
   #220 = Methodref          #214.#856    // com/msxf/uds/uas/sdk/vo/ApplyCustContactVo.setContactRelation:(Ljava/lang/String;)V
   #221 = Methodref          #213.#857    // com/msxf/vopen/dto/req/jd/CheckApplyReqDTO$UserInfoDTO$emergInfoDTO.getEmergTel:()Ljava/lang/String;
   #222 = Methodref          #214.#858    // com/msxf/uds/uas/sdk/vo/ApplyCustContactVo.setContactMobile:(Ljava/lang/String;)V
   #223 = InterfaceMethodref #845.#859    // java/util/List.add:(Ljava/lang/Object;)Z
   #224 = Methodref          #146.#860    // com/msxf/uds/uas/sdk/vo/ApplyVo.setContactList:(Ljava/util/List;)V
   #225 = Fieldref           #388.#861    // com/msxf/vopen/service/biz/impl/jd/JDApplyServiceImpl.areaService:Lcom/msxf/eyas/cms/sdk/service/BaseDicAreaRemoteService;
   #226 = InterfaceMethodref #862.#863    // com/msxf/eyas/cms/sdk/service/BaseDicAreaRemoteService.findAreaCodeByAreaName:(Ljava/lang/String;Z)Ljava/lang/String;
   #227 = Methodref          #146.#864    // com/msxf/uds/uas/sdk/vo/ApplyVo.setAbodeState:(Ljava/lang/String;)V
   #228 = Methodref          #146.#865    // com/msxf/uds/uas/sdk/vo/ApplyVo.setAbodeCity:(Ljava/lang/String;)V
   #229 = Methodref          #146.#866    // com/msxf/uds/uas/sdk/vo/ApplyVo.setAbodeZone:(Ljava/lang/String;)V
   #230 = Class              #867         // com/msxf/vopen/dto/req/CreditAuthCodeReqDTO
   #231 = Methodref          #230.#620    // com/msxf/vopen/dto/req/CreditAuthCodeReqDTO."<init>":()V
   #232 = Methodref          #230.#868    // com/msxf/vopen/dto/req/CreditAuthCodeReqDTO.setAppid:(Ljava/lang/String;)V
   #233 = Methodref          #230.#784    // com/msxf/vopen/dto/req/CreditAuthCodeReqDTO.setProductCode:(Ljava/lang/String;)V
   #234 = Methodref          #230.#808    // com/msxf/vopen/dto/req/CreditAuthCodeReqDTO.setIdNo:(Ljava/lang/String;)V
   #235 = Methodref          #230.#802    // com/msxf/vopen/dto/req/CreditAuthCodeReqDTO.setName:(Ljava/lang/String;)V
   #236 = Methodref          #230.#869    // com/msxf/vopen/dto/req/CreditAuthCodeReqDTO.setUserPhone:(Ljava/lang/String;)V
   #237 = Methodref          #230.#870    // com/msxf/vopen/dto/req/CreditAuthCodeReqDTO.setWhite:(Ljava/lang/String;)V
   #238 = Fieldref           #871.#872    // com/msxf/vopen/constants/YONEnum.N:Lcom/msxf/vopen/constants/YONEnum;
   #239 = Methodref          #230.#873    // com/msxf/vopen/dto/req/CreditAuthCodeReqDTO.setZhimaCredit:(Lcom/msxf/vopen/constants/YONEnum;)V
   #240 = Class              #874         // com/msxf/eyas/cmc/vo/user/UserMobileRegVo
   #241 = Methodref          #240.#620    // com/msxf/eyas/cmc/vo/user/UserMobileRegVo."<init>":()V
   #242 = Methodref          #875.#876    // com/msxf/vopen/util/OpenUtil.generateLoginPassWord:()Ljava/lang/String;
   #243 = Methodref          #240.#877    // com/msxf/eyas/cmc/vo/user/UserMobileRegVo.setMobile:(Ljava/lang/String;)V
   #244 = Methodref          #878.#879    // com/msxf/vopen/util/SHAUtil.encryptSHA256:(Ljava/lang/String;)Ljava/lang/String;
   #245 = Methodref          #240.#880    // com/msxf/eyas/cmc/vo/user/UserMobileRegVo.setPassword:(Ljava/lang/String;)V
   #246 = Class              #881         // com/msxf/eyas/cmc/vo/base/ApiApplicationVO
   #247 = Methodref          #882.#883    // com/msxf/eyas/common/util/BeanUtil.copyProperties:(Ljava/lang/Object;Ljava/lang/Class;)Ljava/lang/Object;
   #248 = Methodref          #240.#884    // com/msxf/eyas/cmc/vo/user/UserMobileRegVo.setApiApplication:(Lcom/msxf/eyas/cmc/vo/base/ApiApplicationVO;)V
   #249 = Methodref          #788.#885    // com/msxf/vopen/support/ApiCaller.getDeviceInfo:()Lcom/msxf/eyas/cmc/vo/base/DeviceInfo;
   #250 = Class              #886         // com/msxf/eyas/cmc/vo/base/DeviceInfo
   #251 = Methodref          #240.#887    // com/msxf/eyas/cmc/vo/user/UserMobileRegVo.setDeviceInfo:(Lcom/msxf/eyas/cmc/vo/base/DeviceInfo;)V
   #252 = String             #888         // 2099-12-30
   #253 = Class              #889         // java/lang/String
   #254 = String             #890         // yyyy-MM-dd
   #255 = Methodref          #753.#891    // org/apache/commons/lang3/time/DateUtils.parseDate:(Ljava/lang/String;[Ljava/lang/String;)Ljava/util/Date;
   #256 = Class              #892         // java/text/ParseException
   #257 = Methodref          #256.#893    // java/text/ParseException.printStackTrace:()V
   #258 = Class              #894         // com/msxf/eyas/cmc/vo/cust/CustBaseInfoVO
   #259 = Methodref          #258.#620    // com/msxf/eyas/cmc/vo/cust/CustBaseInfoVO."<init>":()V
   #260 = Methodref          #258.#782    // com/msxf/eyas/cmc/vo/cust/CustBaseInfoVO.setUniqueId:(Ljava/lang/String;)V
   #261 = Methodref          #258.#802    // com/msxf/eyas/cmc/vo/cust/CustBaseInfoVO.setName:(Ljava/lang/String;)V
   #262 = Methodref          #258.#895    // com/msxf/eyas/cmc/vo/cust/CustBaseInfoVO.setIdType:(Ljava/lang/String;)V
   #263 = Methodref          #258.#808    // com/msxf/eyas/cmc/vo/cust/CustBaseInfoVO.setIdNo:(Ljava/lang/String;)V
   #264 = Methodref          #258.#809    // com/msxf/eyas/cmc/vo/cust/CustBaseInfoVO.setCellphone:(Ljava/lang/String;)V
   #265 = String             #896         // 80010114
   #266 = Methodref          #258.#897    // com/msxf/eyas/cmc/vo/cust/CustBaseInfoVO.setCustSourceCooperator:(Ljava/lang/String;)V
   #267 = String             #898         // vopen
   #268 = Methodref          #258.#899    // com/msxf/eyas/cmc/vo/cust/CustBaseInfoVO.setCustSourceTerm:(Ljava/lang/String;)V
   #269 = Methodref          #258.#864    // com/msxf/eyas/cmc/vo/cust/CustBaseInfoVO.setAbodeState:(Ljava/lang/String;)V
   #270 = Methodref          #258.#865    // com/msxf/eyas/cmc/vo/cust/CustBaseInfoVO.setAbodeCity:(Ljava/lang/String;)V
   #271 = Methodref          #258.#866    // com/msxf/eyas/cmc/vo/cust/CustBaseInfoVO.setAbodeZone:(Ljava/lang/String;)V
   #272 = Methodref          #258.#828    // com/msxf/eyas/cmc/vo/cust/CustBaseInfoVO.setAbodeDetail:(Ljava/lang/String;)V
   #273 = Methodref          #258.#900    // com/msxf/eyas/cmc/vo/cust/CustBaseInfoVO.setIdLastDate:(Ljava/util/Date;)V
   #274 = Class              #901         // com/msxf/eyas/cmc/vo/cust/CustOccupationInfoVO
   #275 = Methodref          #274.#620    // com/msxf/eyas/cmc/vo/cust/CustOccupationInfoVO."<init>":()V
   #276 = Methodref          #486.#902    // com/msxf/vopen/dto/req/jd/CheckApplyReqDTO$UserInfoDTO.getSchool:()Ljava/lang/String;
   #277 = String             #903         // /
   #278 = Methodref          #486.#904    // com/msxf/vopen/dto/req/jd/CheckApplyReqDTO$UserInfoDTO.getUnitName:()Ljava/lang/String;
   #279 = Methodref          #274.#905    // com/msxf/eyas/cmc/vo/cust/CustOccupationInfoVO.setUnitName:(Ljava/lang/String;)V
   #280 = Methodref          #486.#906    // com/msxf/vopen/dto/req/jd/CheckApplyReqDTO$UserInfoDTO.getWorkAddressProvince:()Ljava/lang/String;
   #281 = Methodref          #274.#907    // com/msxf/eyas/cmc/vo/cust/CustOccupationInfoVO.setEmpProvince:(Ljava/lang/String;)V
   #282 = Methodref          #486.#908    // com/msxf/vopen/dto/req/jd/CheckApplyReqDTO$UserInfoDTO.getWorkAddressCity:()Ljava/lang/String;
   #283 = Methodref          #274.#909    // com/msxf/eyas/cmc/vo/cust/CustOccupationInfoVO.setEmpCity:(Ljava/lang/String;)V
   #284 = Methodref          #486.#910    // com/msxf/vopen/dto/req/jd/CheckApplyReqDTO$UserInfoDTO.getWorkAddressArea:()Ljava/lang/String;
   #285 = Methodref          #274.#911    // com/msxf/eyas/cmc/vo/cust/CustOccupationInfoVO.setEmpZone:(Ljava/lang/String;)V
   #286 = Methodref          #486.#912    // com/msxf/vopen/dto/req/jd/CheckApplyReqDTO$UserInfoDTO.getWorkAddressDetail:()Ljava/lang/String;
   #287 = Methodref          #274.#913    // com/msxf/eyas/cmc/vo/cust/CustOccupationInfoVO.setEmpAddr:(Ljava/lang/String;)V
   #288 = Methodref          #486.#914    // com/msxf/vopen/dto/req/jd/CheckApplyReqDTO$UserInfoDTO.getUnitTel:()Ljava/lang/String;
   #289 = Methodref          #274.#915    // com/msxf/eyas/cmc/vo/cust/CustOccupationInfoVO.setEmpPhone:(Ljava/lang/String;)V
   #290 = Class              #916         // com/msxf/eyas/cmc/vo/cust/CustContactVO
   #291 = Methodref          #290.#620    // com/msxf/eyas/cmc/vo/cust/CustContactVO."<init>":()V
   #292 = Methodref          #290.#782    // com/msxf/eyas/cmc/vo/cust/CustContactVO.setUniqueId:(Ljava/lang/String;)V
   #293 = Methodref          #290.#853    // com/msxf/eyas/cmc/vo/cust/CustContactVO.setContactName:(Ljava/lang/String;)V
   #294 = Methodref          #290.#858    // com/msxf/eyas/cmc/vo/cust/CustContactVO.setContactMobile:(Ljava/lang/String;)V
   #295 = Methodref          #290.#856    // com/msxf/eyas/cmc/vo/cust/CustContactVO.setContactRelation:(Ljava/lang/String;)V
   #296 = Class              #917         // com/msxf/eyas/cmc/vo/cust/CustInfoVO
   #297 = Methodref          #296.#620    // com/msxf/eyas/cmc/vo/cust/CustInfoVO."<init>":()V
   #298 = Methodref          #296.#782    // com/msxf/eyas/cmc/vo/cust/CustInfoVO.setUniqueId:(Ljava/lang/String;)V
   #299 = Methodref          #296.#918    // com/msxf/eyas/cmc/vo/cust/CustInfoVO.setBaseInfo:(Lcom/msxf/eyas/cmc/vo/cust/CustBaseInfoVO;)V
   #300 = Methodref          #296.#919    // com/msxf/eyas/cmc/vo/cust/CustInfoVO.setOccupationInfo:(Lcom/msxf/eyas/cmc/vo/cust/CustOccupationInfoVO;)V
   #301 = Methodref          #296.#860    // com/msxf/eyas/cmc/vo/cust/CustInfoVO.setContactList:(Ljava/util/List;)V
   #302 = Methodref          #253.#920    // java/lang/String.hashCode:()I
   #303 = String             #921         // PARENT
   #304 = String             #922         // SPOUSE
   #305 = String             #923         // CHILDREN
   #306 = String             #924         // KINSMAN
   #307 = String             #925         // CLASSMATE
   #308 = String             #926         // COLLEAGUE
   #309 = String             #927         // FRIEND
   #310 = Fieldref           #928.#929    // com/msxf/eyas/enums/ContactRelationTypeEnum.FATHER:Lcom/msxf/eyas/enums/ContactRelationTypeEnum;
   #311 = Methodref          #928.#797    // com/msxf/eyas/enums/ContactRelationTypeEnum.getStandardValue:()Ljava/lang/String;
   #312 = Fieldref           #928.#930    // com/msxf/eyas/enums/ContactRelationTypeEnum.CONSORT:Lcom/msxf/eyas/enums/ContactRelationTypeEnum;
   #313 = Fieldref           #928.#931    // com/msxf/eyas/enums/ContactRelationTypeEnum.CHILD:Lcom/msxf/eyas/enums/ContactRelationTypeEnum;
   #314 = Fieldref           #928.#932    // com/msxf/eyas/enums/ContactRelationTypeEnum.OTHER:Lcom/msxf/eyas/enums/ContactRelationTypeEnum;
   #315 = Fieldref           #928.#933    // com/msxf/eyas/enums/ContactRelationTypeEnum.SCHOOLMATE:Lcom/msxf/eyas/enums/ContactRelationTypeEnum;
   #316 = Fieldref           #928.#934    // com/msxf/eyas/enums/ContactRelationTypeEnum.COLLEAGUE:Lcom/msxf/eyas/enums/ContactRelationTypeEnum;
   #317 = Fieldref           #928.#935    // com/msxf/eyas/enums/ContactRelationTypeEnum.FRIEND:Lcom/msxf/eyas/enums/ContactRelationTypeEnum;
   #318 = Methodref          #724.#936    // com/msxf/uds/uas/sdk/vo/ApplyQueryDetailVo.getContractNo:()Ljava/lang/String;
   #319 = Class              #937         // com/msxf/uds/uas/newsdk/sign/vo/CreateContractNoVo
   #320 = Methodref          #319.#620    // com/msxf/uds/uas/newsdk/sign/vo/CreateContractNoVo."<init>":()V
   #321 = Methodref          #724.#641    // com/msxf/uds/uas/sdk/vo/ApplyQueryDetailVo.getApplyNo:()Ljava/lang/String;
   #322 = Methodref          #319.#718    // com/msxf/uds/uas/newsdk/sign/vo/CreateContractNoVo.setApplyNo:(Ljava/lang/String;)V
   #323 = Methodref          #319.#938    // com/msxf/uds/uas/newsdk/sign/vo/CreateContractNoVo.setSysCode:(Ljava/lang/String;)V
   #324 = Fieldref           #388.#939    // com/msxf/vopen/service/biz/impl/jd/JDApplyServiceImpl.signService:Lcom/msxf/uds/uas/newsdk/sign/service/ISignService;
   #325 = InterfaceMethodref #940.#941    // com/msxf/uds/uas/newsdk/sign/service/ISignService.createContractNo:(Lcom/msxf/uds/uas/newsdk/sign/vo/CreateContractNoVo;)Ljava/lang/String;
   #326 = Class              #942         // com/msxf/vopen/entity/ThirdRelationEntity
   #327 = Methodref          #326.#620    // com/msxf/vopen/entity/ThirdRelationEntity."<init>":()V
   #328 = Methodref          #326.#868    // com/msxf/vopen/entity/ThirdRelationEntity.setAppid:(Ljava/lang/String;)V
   #329 = Methodref          #326.#943    // com/msxf/vopen/entity/ThirdRelationEntity.setAppCode:(Ljava/lang/String;)V
   #330 = Methodref          #326.#944    // com/msxf/vopen/entity/ThirdRelationEntity.setThirdApplyNo:(Ljava/lang/String;)V
   #331 = Methodref          #326.#718    // com/msxf/vopen/entity/ThirdRelationEntity.setApplyNo:(Ljava/lang/String;)V
   #332 = Methodref          #326.#945    // com/msxf/vopen/entity/ThirdRelationEntity.setThirdProductCode:(Ljava/lang/String;)V
   #333 = Methodref          #326.#784    // com/msxf/vopen/entity/ThirdRelationEntity.setProductCode:(Ljava/lang/String;)V
   #334 = Methodref          #326.#946    // com/msxf/vopen/entity/ThirdRelationEntity.setThirdUserId:(Ljava/lang/String;)V
   #335 = Methodref          #326.#782    // com/msxf/vopen/entity/ThirdRelationEntity.setUniqueId:(Ljava/lang/String;)V
   #336 = Class              #947         // java/util/Date
   #337 = Methodref          #336.#620    // java/util/Date."<init>":()V
   #338 = Methodref          #326.#948    // com/msxf/vopen/entity/ThirdRelationEntity.setCreateTime:(Ljava/util/Date;)V
   #339 = String             #949         // /upload/crpl_msjr/ocr/
   #340 = Methodref          #139.#950    // java/lang/StringBuilder.append:(I)Ljava/lang/StringBuilder;
   #341 = String             #951         // .txt
   #342 = Fieldref           #388.#952    // com/msxf/vopen/service/biz/impl/jd/JDApplyServiceImpl.host:Ljava/lang/String;
   #343 = Fieldref           #388.#953    // com/msxf/vopen/service/biz/impl/jd/JDApplyServiceImpl.port:Ljava/lang/Integer;
   #344 = Fieldref           #388.#954    // com/msxf/vopen/service/biz/impl/jd/JDApplyServiceImpl.username:Ljava/lang/String;
   #345 = Fieldref           #388.#955    // com/msxf/vopen/service/biz/impl/jd/JDApplyServiceImpl.secret:Ljava/lang/String;
   #346 = Methodref          #956.#957    // com/msxf/vopen/util/FtpUtil.downloadViaSFTP:(Ljava/lang/String;ILjava/lang/String;Ljava/lang/String;Ljava/lang/String;Ljava/lang/String;)Ljava/io/InputStream;
   #347 = String             #958         // UTF-8
   #348 = Methodref          #959.#960    // org/apache/commons/io/Charsets.toCharset:(Ljava/lang/String;)Ljava/nio/charset/Charset;
   #349 = Methodref          #961.#962    // org/apache/commons/io/IOUtils.toString:(Ljava/io/InputStream;Ljava/nio/charset/Charset;)Ljava/lang/String;
   #350 = Class              #963         // com/msxf/vopen/exception/JdOcrException
   #351 = Fieldref           #964.#965    // com/msxf/vopen/constants/CodeEnum.OCR_EXCEPTION:Lcom/msxf/vopen/constants/CodeEnum;
   #352 = Methodref          #964.#664    // com/msxf/vopen/constants/CodeEnum.getCode:()I
   #353 = String             #966         // 京东OCR文件流为空!
   #354 = Methodref          #350.#967    // com/msxf/vopen/exception/JdOcrException."<init>":(ILjava/lang/String;)V
   #355 = Methodref          #696.#968    // com/msxf/vopen/entity/ChannelEntity.getSecretKey:()Ljava/lang/String;
   #356 = Methodref          #969.#970    // com/msxf/vopen/util/jd/DESUtil.decrypt2Byte:(Ljava/lang/String;Ljava/lang/String;)[B
   #357 = Class              #971         // java/io/ByteArrayInputStream
   #358 = Methodref          #357.#972    // java/io/ByteArrayInputStream."<init>":([B)V
   #359 = Fieldref           #388.#973    // com/msxf/vopen/service/biz/impl/jd/JDApplyServiceImpl.ifsService:Lcom/msxf/eyas/ifs/IFSService;
   #360 = String             #974         // 141001
   #361 = Methodref          #388.#975    // com/msxf/vopen/service/biz/impl/jd/JDApplyServiceImpl.parseOCRCategory:(I)Ljava/lang/String;
   #362 = String             #976         // jpg
   #363 = InterfaceMethodref #977.#978    // com/msxf/eyas/ifs/IFSService.upload:(Ljava/lang/String;Ljava/lang/String;Ljava/lang/String;Ljava/lang/String;Ljava/io/InputStream;)Ljava/lang/Long;
   #364 = Methodref          #979.#980    // java/lang/Long.longValue:()J
   #365 = String             #981         // 上传京东用户OCR信息成功,文件id:{}
   #366 = Methodref          #979.#982    // java/lang/Long.valueOf:(J)Ljava/lang/Long;
   #367 = InterfaceMethodref #652.#983    // org/slf4j/Logger.info:(Ljava/lang/String;Ljava/lang/Object;)V
   #368 = Methodref          #253.#984    // java/lang/String.valueOf:(J)Ljava/lang/String;
   #369 = Fieldref           #985.#986    // com/msxf/vopen/constants/IFSEnum.F:Lcom/msxf/vopen/constants/IFSEnum;
   #370 = Methodref          #985.#987    // com/msxf/vopen/constants/IFSEnum.name:()Ljava/lang/String;
   #371 = Fieldref           #985.#988    // com/msxf/vopen/constants/IFSEnum.R:Lcom/msxf/vopen/constants/IFSEnum;
   #372 = Fieldref           #985.#989    // com/msxf/vopen/constants/IFSEnum.P:Lcom/msxf/vopen/constants/IFSEnum;
   #373 = Methodref          #990.#991    // java/io/InputStream.close:()V
   #374 = Methodref          #956.#992    // com/msxf/vopen/util/FtpUtil.logoutViaSFTP:()V
   #375 = InterfaceMethodref #977.#993    // com/msxf/eyas/ifs/IFSService.link:(Ljava/lang/String;Ljava/lang/String;Ljava/util/List;Ljava/util/List;)V
   #376 = String             #994         // F
   #377 = String             #995         // R
   #378 = String             #996         // D
   #379 = Class              #997         // com/msxf/vopen/dto/req/jd/NotifyIOCRReqDTO
   #380 = String             #998         // 京东OCR请求参数:{}
   #381 = InterfaceMethodref #652.#999    // org/slf4j/Logger.warn:(Ljava/lang/String;Ljava/lang/Object;)V
   #382 = String             #1000        // JD
   #383 = Methodref          #379.#646    // com/msxf/vopen/dto/req/jd/NotifyIOCRReqDTO.getUserId:()Ljava/lang/String;
   #384 = InterfaceMethodref #642.#1001   // com/msxf/vopen/repository/ThirdRelationRepository.findByThirdUserId:(Ljava/lang/String;Ljava/lang/String;)Lcom/msxf/vopen/entity/ThirdRelationEntity;
   #385 = String             #1002        // 京东OCR请求的第三方用信息{}
   #386 = InterfaceMethodref #721.#647    // com/msxf/vopen/service/biz/jd/JDNotifyService.uploadJDUserOCRInfo:(Ljava/lang/String;Ljava/lang/String;)V
   #387 = Methodref          #655.#651    // com/msxf/vopen/constants/JDRespCodeEnum.getMessage:()Ljava/lang/String;
   #388 = Class              #1003        // com/msxf/vopen/service/biz/impl/jd/JDApplyServiceImpl
   #389 = Methodref          #1004.#1005  // org/slf4j/LoggerFactory.getLogger:(Ljava/lang/Class;)Lorg/slf4j/Logger;
   #390 = Class              #1006        // com/msxf/vopen/service/biz/jd/JDApplyService
   #391 = Utf8               logger
   #392 = Utf8               Lorg/slf4j/Logger;
   #393 = Utf8               host
   #394 = Utf8               Ljava/lang/String;
   #395 = Utf8               RuntimeVisibleAnnotations
   #396 = Utf8               Lorg/springframework/beans/factory/annotation/Value;
   #397 = Utf8               value
   #398 = Utf8               ${jd.sftp.host}
   #399 = Utf8               port
   #400 = Utf8               Ljava/lang/Integer;
   #401 = Utf8               ${jd.sftp.port}
   #402 = Utf8               secret
   #403 = Utf8               ${jd.sftp.secret}
   #404 = Utf8               username
   #405 = Utf8               ${jd.sftp.username}
   #406 = Utf8               certPassword
   #407 = Utf8               ${jd.cert.password}
   #408 = Utf8               redis
   #409 = Utf8               Lredis/clients/jedis/JedisCluster;
   #410 = Utf8               Lorg/springframework/beans/factory/annotation/Autowired;
   #411 = Utf8               ifsService
   #412 = Utf8               Lcom/msxf/eyas/ifs/IFSService;
   #413 = Utf8               dscService
   #414 = Utf8               Lcom/msxf/eyas/dsc/DSCService;
   #415 = Utf8               bizUserService
   #416 = Utf8               Lcom/msxf/vopen/service/biz/BizUserService;
   #417 = Utf8               bizHelpService
   #418 = Utf8               Lcom/msxf/vopen/service/biz/BizHelpService;
   #419 = Utf8               appBaseService
   #420 = Utf8               Lcom/msxf/vopen/service/AppBaseService;
   #421 = Utf8               jdNotifyService
   #422 = Utf8               Lcom/msxf/vopen/service/biz/jd/JDNotifyService;
   #423 = Utf8               bizNotifyService
   #424 = Utf8               Lcom/msxf/vopen/service/biz/BizNotifyService;
   #425 = Utf8               jdUserDao
   #426 = Utf8               Lcom/msxf/vopen/repository/ThirdRelationRepository;
   #427 = Utf8               commonUtil
   #428 = Utf8               Lcom/msxf/vopen/util/jd/JDCommonUtil;
   #429 = Utf8               signService
   #430 = Utf8               Lcom/msxf/uds/uas/newsdk/sign/service/ISignService;
   #431 = Utf8               Lcom/msxf/eyas/common/remoting/annotation/RemoteClient;
   #432 = Utf8               ${remote.uas}
   #433 = Utf8               cmcUserService
   #434 = Utf8               Lcom/msxf/eyas/cmc/sdk/user/IUserService;
   #435 = Utf8               ${remote.cmc}
   #436 = Utf8               iCustInfoService
   #437 = Utf8               Lcom/msxf/eyas/cmc/sdk/cust/ICustInfoService;
   #438 = Utf8               areaService
   #439 = Utf8               Lcom/msxf/eyas/cms/sdk/service/BaseDicAreaRemoteService;
   #440 = Utf8               ${remote.cms}
   #441 = Utf8               iApplicationService
   #442 = Utf8               Lcom/msxf/uds/uas/sdk/IApplicationService;
   #443 = Utf8               userInfoQueryService
   #444 = Utf8               Lcom/msxf/eyas/cmc/sdk/user/IUserInfoQueryService;
   #445 = Utf8               <init>
   #446 = Utf8               ()V
   #447 = Utf8               Code
   #448 = Utf8               LineNumberTable
   #449 = Utf8               LocalVariableTable
   #450 = Utf8               this
   #451 = Utf8               Lcom/msxf/vopen/service/biz/impl/jd/JDApplyServiceImpl;
   #452 = Utf8               checkApply
   #453 = Utf8               (Lcom/msxf/vopen/dto/jd/CommonRequest;)Lcom/msxf/vopen/dto/jd/CommonResponse;
   #454 = Utf8               e
   #455 = Utf8               Ljava/lang/Exception;
   #456 = Utf8               reqParam
   #457 = Utf8               Lcom/msxf/eyas/cmc/CMCException;
   #458 = Utf8               userRegVo
   #459 = Utf8               Lcom/msxf/eyas/cmc/vo/user/UserMobileRegVo;
   #460 = Utf8               loginResultVO
   #461 = Utf8               Lcom/msxf/eyas/cmc/vo/user/LoginResultVO;
   #462 = Utf8               custInfo
   #463 = Utf8               Lcom/msxf/eyas/cmc/vo/cust/CustInfoVO;
   #464 = Utf8               Lcom/msxf/uds/uas/exception/UASException;
   #465 = Utf8               authCodeResp
   #466 = Utf8               Lcom/msxf/vopen/constants/CommonResult;
   #467 = Utf8               creditAuthCodeResp
   #468 = Utf8               Lcom/msxf/vopen/dto/resp/CreditAuthCodeRespDTO;
   #469 = Utf8               authCode
   #470 = Utf8               uniqueId
   #471 = Utf8               userInfo
   #472 = Utf8               Lcom/msxf/eyas/cmc/vo/user/UserBaseInfoVO;
   #473 = Utf8               userId
   #474 = Utf8               Ljava/lang/Long;
   #475 = Utf8               applyVo
   #476 = Utf8               Lcom/msxf/uds/uas/sdk/vo/ApplyVo;
   #477 = Utf8               requestVo
   #478 = Utf8               Lcom/msxf/uds/uas/sdk/vo/ApplyQueryRequestVo;
   #479 = Utf8               detailVo
   #480 = Utf8               Lcom/msxf/uds/uas/sdk/vo/ApplyQueryDetailVo;
   #481 = Utf8               reqData
   #482 = Utf8               Lcom/msxf/vopen/dto/jd/CommonRequest;
   #483 = Utf8               req
   #484 = Utf8               Lcom/msxf/vopen/dto/req/jd/CheckApplyReqDTO;
   #485 = Utf8               user
   #486 = Class              #1007        // com/msxf/vopen/dto/req/jd/CheckApplyReqDTO$UserInfoDTO
   #487 = Utf8               UserInfoDTO
   #488 = Utf8               InnerClasses
   #489 = Utf8               Lcom/msxf/vopen/dto/req/jd/CheckApplyReqDTO$UserInfoDTO;
   #490 = Utf8               apiCaller
   #491 = Utf8               Lcom/msxf/vopen/support/ApiCaller;
   #492 = Utf8               channel
   #493 = Utf8               Lcom/msxf/vopen/entity/ChannelEntity;
   #494 = Utf8               applyNo
   #495 = Utf8               feeRate
   #496 = Utf8               forJudge
   #497 = Utf8               Lcom/msxf/vopen/entity/ThirdRelationEntity;
   #498 = Utf8               StackMapTable
   #499 = Class              #1003        // com/msxf/vopen/service/biz/impl/jd/JDApplyServiceImpl
   #500 = Class              #1008        // com/msxf/vopen/dto/jd/CommonRequest
   #501 = Class              #623         // com/msxf/vopen/dto/req/jd/CheckApplyReqDTO
   #502 = Class              #1007        // com/msxf/vopen/dto/req/jd/CheckApplyReqDTO$UserInfoDTO
   #503 = Class              #1009        // com/msxf/vopen/support/ApiCaller
   #504 = Class              #1010        // com/msxf/vopen/entity/ChannelEntity
   #505 = Class              #889         // java/lang/String
   #506 = Class              #942         // com/msxf/vopen/entity/ThirdRelationEntity
   #507 = Class              #648         // java/lang/Exception
   #508 = Class              #1011        // com/msxf/vopen/constants/CommonResult
   #509 = Class              #669         // com/msxf/vopen/dto/resp/CreditAuthCodeRespDTO
   #510 = Class              #1012        // com/msxf/eyas/cmc/vo/user/UserBaseInfoVO
   #511 = Class              #1013        // java/lang/Long
   #512 = Class              #874         // com/msxf/eyas/cmc/vo/user/UserMobileRegVo
   #513 = Class              #1014        // com/msxf/eyas/cmc/vo/user/LoginResultVO
   #514 = Class              #684         // com/msxf/eyas/cmc/CMCException
   #515 = Class              #917         // com/msxf/eyas/cmc/vo/cust/CustInfoVO
   #516 = Class              #779         // com/msxf/uds/uas/sdk/vo/ApplyVo
   #517 = Class              #707         // com/msxf/uds/uas/exception/UASException
   #518 = Utf8               Exceptions
   #519 = Utf8               jdResp
   #520 = Utf8               (Ljava/lang/String;Lcom/msxf/vopen/dto/req/jd/CheckApplyReqDTO;Ljava/lang/String;)Lcom/msxf/vopen/dto/resp/jd/CheckApplyRespDTO;
   #521 = Utf8               applyDetailQuery
   #522 = Utf8               applyDetail
   #523 = Utf8               response
   #524 = Utf8               Lcom/msxf/vopen/dto/resp/jd/CheckApplyRespDTO;
   #525 = Class              #717         // com/msxf/uds/uas/sdk/vo/ApplyQueryRequestVo
   #526 = Class              #1015        // com/msxf/uds/uas/sdk/vo/ApplyQueryDetailVo
   #527 = Class              #739         // com/msxf/vopen/dto/resp/jd/CheckApplyRespDTO
   #528 = Utf8               getProductInfo
   #529 = Utf8               ProductInfoDTO
   #530 = Utf8               (Ljava/lang/String;Ljava/lang/String;)Lcom/msxf/vopen/dto/resp/jd/CheckApplyRespDTO$ProductInfoDTO;
   #531 = Utf8               applyProduct
   #532 = Utf8               productInfo
   #533 = Utf8               Lcom/msxf/vopen/dto/resp/jd/CheckApplyRespDTO$ProductInfoDTO;
   #534 = Utf8               getApplyVo
   #535 = Utf8               (Lcom/msxf/vopen/dto/req/jd/CheckApplyReqDTO;Ljava/lang/String;Lcom/msxf/vopen/support/ApiCaller;Ljava/lang/String;Ljava/lang/String;Ljava/lang/String;Ljava/lang/Long;)Lcom/msxf/uds/uas/sdk/vo/ApplyVo;
   #536 = Utf8               custContact
   #537 = Utf8               Lcom/msxf/uds/uas/sdk/vo/ApplyCustContactVo;
   #538 = Utf8               emerge
   #539 = Utf8               emergInfoDTO
   #540 = Utf8               Lcom/msxf/vopen/dto/req/jd/CheckApplyReqDTO$UserInfoDTO$emergInfoDTO;
   #541 = Utf8               apply
   #542 = Utf8               requestNo
   #543 = Utf8               provinceCode
   #544 = Utf8               cityCode
   #545 = Utf8               zoneCode
   #546 = Utf8               contactList
   #547 = Utf8               Ljava/util/List;
   #548 = Utf8               emergList
   #549 = Utf8               LocalVariableTypeTable
   #550 = Utf8               Ljava/util/List<Lcom/msxf/uds/uas/sdk/vo/ApplyCustContactVo;>;
   #551 = Utf8               Ljava/util/List<Lcom/msxf/vopen/dto/req/jd/CheckApplyReqDTO$UserInfoDTO$emergInfoDTO;>;
   #552 = Class              #1016        // java/util/List
   #553 = Class              #1017        // java/util/Iterator
   #554 = Utf8               getAuthCodeReqParams
   #555 = Utf8               (Lcom/msxf/vopen/dto/req/jd/CheckApplyReqDTO$UserInfoDTO;)Lcom/msxf/vopen/dto/req/CreditAuthCodeReqDTO;
   #556 = Utf8               creditAuthCodeReq
   #557 = Utf8               Lcom/msxf/vopen/dto/req/CreditAuthCodeReqDTO;
   #558 = Utf8               mobileRegParams
   #559 = Utf8               (Lcom/msxf/vopen/dto/req/jd/CheckApplyReqDTO$UserInfoDTO;Lcom/msxf/vopen/support/ApiCaller;)Lcom/msxf/eyas/cmc/vo/user/UserMobileRegVo;
   #560 = Utf8               loginPass
   #561 = Utf8               createCustParams
   #562 = Utf8               (Lcom/msxf/vopen/dto/req/jd/CheckApplyReqDTO;Ljava/lang/String;)Lcom/msxf/eyas/cmc/vo/cust/CustInfoVO;
   #563 = Utf8               Ljava/text/ParseException;
   #564 = Utf8               Lcom/msxf/eyas/cmc/vo/cust/CustContactVO;
   #565 = Utf8               defaultDate
   #566 = Utf8               Ljava/util/Date;
   #567 = Utf8               custBaseInfo
   #568 = Utf8               Lcom/msxf/eyas/cmc/vo/cust/CustBaseInfoVO;
   #569 = Utf8               custOccupationInfo
   #570 = Utf8               Lcom/msxf/eyas/cmc/vo/cust/CustOccupationInfoVO;
   #571 = Utf8               Ljava/util/List<Lcom/msxf/eyas/cmc/vo/cust/CustContactVO;>;
   #572 = Class              #947         // java/util/Date
   #573 = Class              #892         // java/text/ParseException
   #574 = Class              #894         // com/msxf/eyas/cmc/vo/cust/CustBaseInfoVO
   #575 = Class              #901         // com/msxf/eyas/cmc/vo/cust/CustOccupationInfoVO
   #576 = Utf8               parseContactRelation
   #577 = Utf8               (Ljava/lang/String;)Ljava/lang/String;
   #578 = Utf8               emergRelation
   #579 = Utf8               createContractNo
   #580 = Utf8               (Lcom/msxf/uds/uas/sdk/vo/ApplyQueryDetailVo;)Ljava/lang/String;
   #581 = Utf8               contractNoVo
   #582 = Utf8               Lcom/msxf/uds/uas/newsdk/sign/vo/CreateContractNoVo;
   #583 = Utf8               contractNo
   #584 = Utf8               saveJDUserInfo
   #585 = Utf8               (Lcom/msxf/vopen/dto/req/jd/CheckApplyReqDTO;Ljava/lang/String;Ljava/lang/String;)Lcom/msxf/vopen/entity/ThirdRelationEntity;
   #586 = Utf8               entity
   #587 = Utf8               uploadJDUserOCRInfo
   #588 = Utf8               (Ljava/lang/String;Ljava/lang/String;)V
   #589 = Utf8               remoteUrl
   #590 = Utf8               content
   #591 = Utf8               imgBytes
   #592 = Utf8               [B
   #593 = Utf8               imgStream
   #594 = Utf8               Ljava/io/InputStream;
   #595 = Utf8               fileId
   #596 = Utf8               J
   #597 = Utf8               fileIdList
   #598 = Utf8               fileCategoryList
   #599 = Utf8               fileCategory
   #600 = Utf8               j
   #601 = Utf8               I
   #602 = Utf8               is
   #603 = Utf8               i
   #604 = Utf8               Ljava/util/List<Ljava/lang/Integer;>;
   #605 = Utf8               Ljava/util/List<Ljava/lang/String;>;
   #606 = Class              #1018        // java/io/InputStream
   #607 = Class              #592         // "[B"
   #608 = Class              #1019        // java/lang/Throwable
   #609 = Utf8               parseOCRCategory
   #610 = Utf8               (I)Ljava/lang/String;
   #611 = Utf8               jdCategory
   #612 = Utf8               notifyOCResult
   #613 = Utf8               notifyReq
   #614 = Utf8               Lcom/msxf/vopen/dto/req/jd/NotifyIOCRReqDTO;
   #615 = Utf8               <clinit>
   #616 = Utf8               SourceFile
   #617 = Utf8               JDApplyServiceImpl.java
   #618 = Utf8               Lorg/springframework/stereotype/Service;
   #619 = Utf8               com/msxf/vopen/util/jd/JDCommonUtil
   #620 = NameAndType        #445:#446    // "<init>":()V
   #621 = Class              #1008        // com/msxf/vopen/dto/jd/CommonRequest
   #622 = NameAndType        #1020:#1021  // getRequestData:()Ljava/lang/String;
   #623 = Utf8               com/msxf/vopen/dto/req/jd/CheckApplyReqDTO
   #624 = Class              #1022        // com/alibaba/fastjson/JSONObject
   #625 = NameAndType        #1023:#1024  // parseObject:(Ljava/lang/String;Ljava/lang/Class;)Ljava/lang/Object;
   #626 = Utf8               统计各合作方提交申请次数
   #627 = Utf8               java/lang/Object
   #628 = Utf8               授信申请来自合作方
   #629 = Utf8               jd
   #630 = Class              #1025        // com/msxf/boot/core/util/log/BusinessLogger
   #631 = NameAndType        #1026:#1027  // log:(Ljava/lang/String;[Ljava/lang/Object;)V
   #632 = NameAndType        #1028:#1029  // getUserInfo:()Lcom/msxf/vopen/dto/req/jd/CheckApplyReqDTO$UserInfoDTO;
   #633 = NameAndType        #417:#418    // bizHelpService:Lcom/msxf/vopen/service/biz/BizHelpService;
   #634 = Class              #1030        // com/msxf/vopen/service/biz/BizHelpService
   #635 = NameAndType        #1031:#1032  // getApiCaller:(Ljava/lang/String;)Lcom/msxf/vopen/support/ApiCaller;
   #636 = NameAndType        #419:#420    // appBaseService:Lcom/msxf/vopen/service/AppBaseService;
   #637 = Class              #1033        // com/msxf/vopen/service/AppBaseService
   #638 = NameAndType        #1034:#1035  // getChannelInfo:(Ljava/lang/String;)Lcom/msxf/vopen/entity/ChannelEntity;
   #639 = Utf8
   #640 = NameAndType        #425:#426    // jdUserDao:Lcom/msxf/vopen/repository/ThirdRelationRepository;
   #641 = NameAndType        #1036:#1021  // getApplyNo:()Ljava/lang/String;
   #642 = Class              #1037        // com/msxf/vopen/repository/ThirdRelationRepository
   #643 = NameAndType        #1038:#1039  // findByThirdApplyNo:(Ljava/lang/String;Ljava/lang/String;)Lcom/msxf/vopen/entity/ThirdRelationEntity;
   #644 = NameAndType        #441:#442    // iApplicationService:Lcom/msxf/uds/uas/sdk/IApplicationService;
   #645 = Class              #1040        // com/msxf/uds/uas/sdk/IApplicationService
   #646 = NameAndType        #1041:#1021  // getUserId:()Ljava/lang/String;
   #647 = NameAndType        #587:#588    // uploadJDUserOCRInfo:(Ljava/lang/String;Ljava/lang/String;)V
   #648 = Utf8               java/lang/Exception
   #649 = NameAndType        #391:#392    // logger:Lorg/slf4j/Logger;
   #650 = Utf8               京东OCR用户信息拉取上传异常：[{}]
   #651 = NameAndType        #1042:#1021  // getMessage:()Ljava/lang/String;
   #652 = Class              #1043        // org/slf4j/Logger
   #653 = NameAndType        #1044:#1045  // warn:(Ljava/lang/String;Ljava/lang/Object;Ljava/lang/Object;)V
   #654 = Utf8               com/msxf/vopen/dto/jd/CommonResponse
   #655 = Class              #1046        // com/msxf/vopen/constants/JDRespCodeEnum
   #656 = NameAndType        #1047:#1048  // UNKNOWN_ERROR:Lcom/msxf/vopen/constants/JDRespCodeEnum;
   #657 = Utf8               OCR拉取/上传异常
   #658 = NameAndType        #445:#1049   // "<init>":(Lcom/msxf/vopen/constants/JDRespCodeEnum;Ljava/lang/String;)V
   #659 = NameAndType        #415:#416    // bizUserService:Lcom/msxf/vopen/service/biz/BizUserService;
   #660 = NameAndType        #554:#555    // getAuthCodeReqParams:(Lcom/msxf/vopen/dto/req/jd/CheckApplyReqDTO$UserInfoDTO;)Lcom/msxf/vopen/dto/req/CreditAuthCodeReqDTO;
   #661 = Class              #1050        // com/msxf/vopen/service/biz/BizUserService
   #662 = NameAndType        #1051:#1052  // getCreditAuthCode:(Lcom/msxf/vopen/dto/req/CreditAuthCodeReqDTO;)Lcom/msxf/vopen/constants/CommonResult;
   #663 = Class              #1011        // com/msxf/vopen/constants/CommonResult
   #664 = NameAndType        #1053:#1054  // getCode:()I
   #665 = Class              #1055        // com/alibaba/fastjson/JSON
   #666 = NameAndType        #1056:#1057  // toJSONString:(Ljava/lang/Object;)Ljava/lang/String;
   #667 = Utf8               京东异常:获取征信授权码异常:{},请求参数:[{}]
   #668 = NameAndType        #1058:#1059  // getData:()Ljava/lang/Object;
   #669 = Utf8               com/msxf/vopen/dto/resp/CreditAuthCodeRespDTO
   #670 = NameAndType        #1060:#1021  // getAuthCode:()Ljava/lang/String;
   #671 = NameAndType        #413:#414    // dscService:Lcom/msxf/eyas/dsc/DSCService;
   #672 = NameAndType        #1061:#1021  // getUsername:()Ljava/lang/String;
   #673 = NameAndType        #1062:#1021  // getCertNo:()Ljava/lang/String;
   #674 = Class              #1063        // com/msxf/eyas/dsc/DSCService
   #675 = NameAndType        #1064:#1065  // getUniqueId:(Ljava/lang/String;Ljava/lang/String;)Ljava/lang/String;
   #676 = NameAndType        #443:#444    // userInfoQueryService:Lcom/msxf/eyas/cmc/sdk/user/IUserInfoQueryService;
   #677 = NameAndType        #1066:#1021  // getUserTel:()Ljava/lang/String;
   #678 = Class              #1067        // com/msxf/eyas/cmc/sdk/user/IUserInfoQueryService
   #679 = NameAndType        #1068:#1069  // getBaseUserInfoByMobile:(Ljava/lang/String;)Lcom/msxf/eyas/cmc/vo/user/UserBaseInfoVO;
   #680 = NameAndType        #558:#559    // mobileRegParams:(Lcom/msxf/vopen/dto/req/jd/CheckApplyReqDTO$UserInfoDTO;Lcom/msxf/vopen/support/ApiCaller;)Lcom/msxf/eyas/cmc/vo/user/UserMobileRegVo;
   #681 = NameAndType        #433:#434    // cmcUserService:Lcom/msxf/eyas/cmc/sdk/user/IUserService;
   #682 = Class              #1070        // com/msxf/eyas/cmc/sdk/user/IUserService
   #683 = NameAndType        #1071:#1072  // mobileReg:(Lcom/msxf/eyas/cmc/vo/user/UserMobileRegVo;)Lcom/msxf/eyas/cmc/vo/user/LoginResultVO;
   #684 = Utf8               com/msxf/eyas/cmc/CMCException
   #685 = Utf8               京东异常:手机号注册异常:{},手机号:{}
   #686 = NameAndType        #1073:#1021  // getMobile:()Ljava/lang/String;
   #687 = NameAndType        #561:#562    // createCustParams:(Lcom/msxf/vopen/dto/req/jd/CheckApplyReqDTO;Ljava/lang/String;)Lcom/msxf/eyas/cmc/vo/cust/CustInfoVO;
   #688 = NameAndType        #436:#437    // iCustInfoService:Lcom/msxf/eyas/cmc/sdk/cust/ICustInfoService;
   #689 = Class              #1074        // com/msxf/eyas/cmc/sdk/cust/ICustInfoService
   #690 = NameAndType        #1075:#1076  // createCust:(Lcom/msxf/eyas/cmc/vo/cust/CustInfoVO;)Lcom/msxf/eyas/cmc/vo/user/UserBaseInfoVO;
   #691 = Utf8               京东异常:创建客户异常:{},UUID:{}
   #692 = NameAndType        #1064:#1021  // getUniqueId:()Ljava/lang/String;
   #693 = NameAndType        #423:#424    // bizNotifyService:Lcom/msxf/vopen/service/biz/BizNotifyService;
   #694 = Class              #1014        // com/msxf/eyas/cmc/vo/user/LoginResultVO
   #695 = NameAndType        #1041:#1077  // getUserId:()Ljava/lang/Long;
   #696 = Class              #1010        // com/msxf/vopen/entity/ChannelEntity
   #697 = NameAndType        #1053:#1021  // getCode:()Ljava/lang/String;
   #698 = NameAndType        #1078:#1021  // getYouqianTerminal:()Ljava/lang/String;
   #699 = NameAndType        #1079:#1021  // getYouqianChannel:()Ljava/lang/String;
   #700 = Class              #1080        // com/msxf/vopen/service/biz/BizNotifyService
   #701 = NameAndType        #1081:#1082  // notifyYouqianUserRecommendedInfo:(Ljava/lang/Long;Ljava/lang/String;Ljava/lang/String;Ljava/lang/String;)V
   #702 = Class              #1012        // com/msxf/eyas/cmc/vo/user/UserBaseInfoVO
   #703 = NameAndType        #1083:#1077  // getId:()Ljava/lang/Long;
   #704 = NameAndType        #1084:#1021  // getRequestNo:()Ljava/lang/String;
   #705 = NameAndType        #534:#535    // getApplyVo:(Lcom/msxf/vopen/dto/req/jd/CheckApplyReqDTO;Ljava/lang/String;Lcom/msxf/vopen/support/ApiCaller;Ljava/lang/String;Ljava/lang/String;Ljava/lang/String;Ljava/lang/Long;)Lcom/msxf/uds/uas/sdk/vo/ApplyVo;
   #706 = NameAndType        #541:#1085   // apply:(Lcom/msxf/uds/uas/sdk/vo/ApplyVo;)Ljava/lang/String;
   #707 = Utf8               com/msxf/uds/uas/exception/UASException
   #708 = Utf8               京东异常:提交申请单异常:{},申请单号:{}
   #709 = Class              #1086        // com/msxf/uds/uas/exception/UASErrorCode
   #710 = NameAndType        #1087:#1088  // APPLY_QUERY_SIGN_ORDER:Lcom/msxf/uds/uas/exception/UASErrorCode;
   #711 = NameAndType        #1089:#1021  // getErrorCode:()Ljava/lang/String;
   #712 = NameAndType        #1090:#1091  // equals:(Ljava/lang/Object;)Z
   #713 = NameAndType        #1087:#1048  // APPLY_QUERY_SIGN_ORDER:Lcom/msxf/vopen/constants/JDRespCodeEnum;
   #714 = NameAndType        #445:#1092   // "<init>":(Lcom/msxf/vopen/dto/jd/CommonRequest;Lcom/msxf/vopen/constants/JDRespCodeEnum;)V
   #715 = NameAndType        #584:#585    // saveJDUserInfo:(Lcom/msxf/vopen/dto/req/jd/CheckApplyReqDTO;Ljava/lang/String;Ljava/lang/String;)Lcom/msxf/vopen/entity/ThirdRelationEntity;
   #716 = NameAndType        #1093:#1094  // save:(Ljava/lang/Object;)Ljava/lang/Object;
   #717 = Utf8               com/msxf/uds/uas/sdk/vo/ApplyQueryRequestVo
   #718 = NameAndType        #1095:#1096  // setApplyNo:(Ljava/lang/String;)V
   #719 = NameAndType        #1097:#1098  // getApplyDetail:(Lcom/msxf/uds/uas/sdk/vo/ApplyQueryRequestVo;)Lcom/msxf/uds/uas/sdk/vo/ApplyQueryDetailVo;
   #720 = NameAndType        #421:#422    // jdNotifyService:Lcom/msxf/vopen/service/biz/jd/JDNotifyService;
   #721 = Class              #1099        // com/msxf/vopen/service/biz/jd/JDNotifyService
   #722 = NameAndType        #1100:#1101  // syncNotifyDataPlatformRiskInfo:(Lcom/msxf/vopen/dto/jd/CommonRequest;)V
   #723 = NameAndType        #427:#428    // commonUtil:Lcom/msxf/vopen/util/jd/JDCommonUtil;
   #724 = Class              #1015        // com/msxf/uds/uas/sdk/vo/ApplyQueryDetailVo
   #725 = NameAndType        #1102:#1021  // getAgreementTariffRate:()Ljava/lang/String;
   #726 = NameAndType        #1103:#577   // parseJdSvcfee:(Ljava/lang/String;)Ljava/lang/String;
   #727 = NameAndType        #408:#409    // redis:Lredis/clients/jedis/JedisCluster;
   #728 = Utf8               com/msxf/vopen/constants/RedisConstants
   #729 = Utf8               vopen_jd_notify_apply
   #730 = NameAndType        #1104:#400   // EXPIRE_7DAY:Ljava/lang/Integer;
   #731 = Class              #1105        // java/lang/Integer
   #732 = NameAndType        #1106:#1054  // intValue:()I
   #733 = NameAndType        #1107:#1021  // getNotifyUrl:()Ljava/lang/String;
   #734 = Class              #1108        // redis/clients/jedis/JedisCluster
   #735 = NameAndType        #1109:#1110  // setex:(Ljava/lang/String;ILjava/lang/String;)Ljava/lang/String;
   #736 = NameAndType        #1111:#1048  // SUCCESS:Lcom/msxf/vopen/constants/JDRespCodeEnum;
   #737 = NameAndType        #519:#520    // jdResp:(Ljava/lang/String;Lcom/msxf/vopen/dto/req/jd/CheckApplyReqDTO;Ljava/lang/String;)Lcom/msxf/vopen/dto/resp/jd/CheckApplyRespDTO;
   #738 = NameAndType        #445:#1112   // "<init>":(Lcom/msxf/vopen/dto/jd/CommonRequest;Lcom/msxf/vopen/constants/JDRespCodeEnum;Ljava/lang/String;)V
   #739 = Utf8               com/msxf/vopen/dto/resp/jd/CheckApplyRespDTO
   #740 = NameAndType        #1113:#1096  // setMhtApplyNo:(Ljava/lang/String;)V
   #741 = NameAndType        #1114:#1021  // getStatus:()Ljava/lang/String;
   #742 = NameAndType        #1115:#577   // parseJDApplyStatus:(Ljava/lang/String;)Ljava/lang/String;
   #743 = NameAndType        #1116:#1096  // setCheckStatus:(Ljava/lang/String;)V
   #744 = NameAndType        #1117:#1118  // getAccLmt:()Ljava/math/BigDecimal;
   #745 = NameAndType        #1119:#1120  // parseCent:(Ljava/math/BigDecimal;)Ljava/lang/String;
   #746 = NameAndType        #1121:#1096  // setCheckAmount:(Ljava/lang/String;)V
   #747 = NameAndType        #1122:#1123  // getApplyTime:()Ljava/util/Date;
   #748 = NameAndType        #1124:#1125  // formatJdDate:(Ljava/util/Date;)Ljava/lang/String;
   #749 = NameAndType        #1126:#1096  // setCheckTime:(Ljava/lang/String;)V
   #750 = NameAndType        #1127:#1021  // getApplyProduct:()Ljava/lang/String;
   #751 = NameAndType        #528:#530    // getProductInfo:(Ljava/lang/String;Ljava/lang/String;)Lcom/msxf/vopen/dto/resp/jd/CheckApplyRespDTO$ProductInfoDTO;
   #752 = NameAndType        #1128:#1129  // setProductInfo:(Lcom/msxf/vopen/dto/resp/jd/CheckApplyRespDTO$ProductInfoDTO;)V
   #753 = Class              #1130        // org/apache/commons/lang3/time/DateUtils
   #754 = NameAndType        #1131:#1132  // addDays:(Ljava/util/Date;I)Ljava/util/Date;
   #755 = NameAndType        #1133:#1096  // setExpiryTime:(Ljava/lang/String;)V
   #756 = Utf8               com/msxf/vopen/dto/resp/jd/CheckApplyRespDTO$ProductInfoDTO
   #757 = NameAndType        #1134:#1096  // setProductId:(Ljava/lang/String;)V
   #758 = Utf8               com/msxf/vopen/constants/JDConstants
   #759 = Utf8               0.000483
   #760 = NameAndType        #1135:#1096  // setInterestRate:(Ljava/lang/String;)V
   #761 = Utf8               3,6,9,12
   #762 = NameAndType        #1136:#1096  // setSupportPeriod:(Ljava/lang/String;)V
   #763 = Utf8               0
   #764 = NameAndType        #1137:#1096  // setEarlyRepayment:(Ljava/lang/String;)V
   #765 = Utf8               EQUAL_PRINCIPAL_INTEREST
   #766 = NameAndType        #1138:#1096  // setRepaymentMethod:(Ljava/lang/String;)V
   #767 = Utf8               1
   #768 = NameAndType        #1139:#1096  // setPartialWithdraw:(Ljava/lang/String;)V
   #769 = Utf8               MONTHLY_SAVINGS
   #770 = NameAndType        #1140:#1096  // setInterestsCalculation:(Ljava/lang/String;)V
   #771 = Utf8               0.003
   #772 = NameAndType        #1141:#1096  // setOverdueInterestRate:(Ljava/lang/String;)V
   #773 = Utf8               java/lang/StringBuilder
   #774 = Utf8               服务费率
   #775 = NameAndType        #1142:#1143  // append:(Ljava/lang/String;)Ljava/lang/StringBuilder;
   #776 = Utf8               %/月
   #777 = NameAndType        #1144:#1021  // toString:()Ljava/lang/String;
   #778 = NameAndType        #1145:#1096  // setFeeDesc:(Ljava/lang/String;)V
   #779 = Utf8               com/msxf/uds/uas/sdk/vo/ApplyVo
   #780 = NameAndType        #1146:#1147  // setUserId:(Ljava/lang/Long;)V
   #781 = NameAndType        #1148:#1096  // setApplySerialNo:(Ljava/lang/String;)V
   #782 = NameAndType        #1149:#1096  // setUniqueId:(Ljava/lang/String;)V
   #783 = Utf8               5208
   #784 = NameAndType        #1150:#1096  // setProductCode:(Ljava/lang/String;)V
   #785 = Utf8               com/msxf/vopen/constants/Constants
   #786 = Utf8               VOPEN
   #787 = NameAndType        #1151:#1096  // setSubTerminalType:(Ljava/lang/String;)V
   #788 = Class              #1009        // com/msxf/vopen/support/ApiCaller
   #789 = NameAndType        #1152:#1153  // getApplication:()Lcom/msxf/vopen/support/ApiApplication;
   #790 = Class              #1154        // com/msxf/vopen/support/ApiApplication
   #791 = NameAndType        #1155:#1021  // getCooperator:()Ljava/lang/String;
   #792 = NameAndType        #1156:#1096  // setCooperatorId:(Ljava/lang/String;)V
   #793 = Utf8               PL18
   #794 = NameAndType        #1157:#1096  // setLoanPurpose:(Ljava/lang/String;)V
   #795 = Class              #1158        // com/msxf/eyas/enums/LifeInsurancePlan
   #796 = NameAndType        #1159:#1160  // NO:Lcom/msxf/eyas/enums/LifeInsurancePlan;
   #797 = NameAndType        #1161:#1021  // getStandardValue:()Ljava/lang/String;
   #798 = NameAndType        #1162:#1096  // setJoinLifeInsurance:(Ljava/lang/String;)V
   #799 = Class              #1163        // com/msxf/vopen/constants/PrepayPkgEnum
   #800 = NameAndType        #1159:#1164  // NO:Lcom/msxf/vopen/constants/PrepayPkgEnum;
   #801 = NameAndType        #1165:#1096  // setPrepayPkgInd:(Ljava/lang/String;)V
   #802 = NameAndType        #1166:#1096  // setName:(Ljava/lang/String;)V
   #803 = Class              #1167        // com/msxf/vopen/util/StringUtil
   #804 = NameAndType        #1168:#577   // getGender:(Ljava/lang/String;)Ljava/lang/String;
   #805 = NameAndType        #1169:#1096  // setGender:(Ljava/lang/String;)V
   #806 = NameAndType        #1170:#1171  // getBirth:(Ljava/lang/String;)Ljava/util/Date;
   #807 = NameAndType        #1172:#1173  // setBirth:(Ljava/util/Date;)V
   #808 = NameAndType        #1174:#1096  // setIdNo:(Ljava/lang/String;)V
   #809 = NameAndType        #1175:#1096  // setCellphone:(Ljava/lang/String;)V
   #810 = Utf8               6222368888888888888
   #811 = NameAndType        #1176:#1096  // setBankCardNo:(Ljava/lang/String;)V
   #812 = Utf8               default@msxf.com
   #813 = NameAndType        #1177:#1096  // setEmail:(Ljava/lang/String;)V
   #814 = Utf8               Y
   #815 = NameAndType        #1178:#1096  // setEmpPost:(Ljava/lang/String;)V
   #816 = Utf8               Z
   #817 = NameAndType        #1179:#1096  // setEmpType:(Ljava/lang/String;)V
   #818 = NameAndType        #1180:#1096  // setEmpStructure:(Ljava/lang/String;)V
   #819 = NameAndType        #1181:#474   // DEFAULT_MONTH_INCOME:Ljava/lang/Long;
   #820 = NameAndType        #1182:#1147  // setMonthIncome:(Ljava/lang/Long;)V
   #821 = NameAndType        #1183:#1021  // getHomeAddressProvince:()Ljava/lang/String;
   #822 = NameAndType        #1184:#1096  // setAbodeStateName:(Ljava/lang/String;)V
   #823 = NameAndType        #1185:#1021  // getHomeAddressCity:()Ljava/lang/String;
   #824 = NameAndType        #1186:#1096  // setAbodeCityName:(Ljava/lang/String;)V
   #825 = NameAndType        #1187:#1021  // getHomeAddressArea:()Ljava/lang/String;
   #826 = NameAndType        #1188:#1096  // setAbodeZoneName:(Ljava/lang/String;)V
   #827 = NameAndType        #1189:#1021  // getHomeAddressDetail:()Ljava/lang/String;
   #828 = NameAndType        #1190:#1096  // setAbodeDetail:(Ljava/lang/String;)V
   #829 = NameAndType        #1191:#1096  // setCreditAuthSerialNo:(Ljava/lang/String;)V
   #830 = Utf8               中国银行
   #831 = NameAndType        #1192:#1096  // setBankName:(Ljava/lang/String;)V
   #832 = Utf8               北京市
   #833 = NameAndType        #1193:#1096  // setBankCityName:(Ljava/lang/String;)V
   #834 = NameAndType        #1194:#1096  // setBankProvinceName:(Ljava/lang/String;)V
   #835 = NameAndType        #1195:#1021  // getApplyAmount:()Ljava/lang/String;
   #836 = Class              #1196        // org/apache/commons/lang3/StringUtils
   #837 = NameAndType        #1197:#1198  // isEmpty:(Ljava/lang/CharSequence;)Z
   #838 = NameAndType        #1199:#1200  // parseYuan:(Ljava/lang/String;)Ljava/math/BigDecimal;
   #839 = NameAndType        #1201:#1202  // setApplyLmt:(Ljava/math/BigDecimal;)V
   #840 = NameAndType        #1203:#1021  // getApplyPeriod:()Ljava/lang/String;
   #841 = NameAndType        #1204:#1205  // valueOf:(Ljava/lang/String;)Ljava/lang/Integer;
   #842 = NameAndType        #1206:#1207  // setApplyLoanTerm:(Ljava/lang/Integer;)V
   #843 = Utf8               java/util/ArrayList
   #844 = NameAndType        #1208:#1209  // getEmergList:()Ljava/util/List;
   #845 = Class              #1016        // java/util/List
   #846 = NameAndType        #1210:#1211  // iterator:()Ljava/util/Iterator;
   #847 = Class              #1017        // java/util/Iterator
   #848 = NameAndType        #1212:#1213  // hasNext:()Z
   #849 = NameAndType        #1214:#1059  // next:()Ljava/lang/Object;
   #850 = Utf8               com/msxf/vopen/dto/req/jd/CheckApplyReqDTO$UserInfoDTO$emergInfoDTO
   #851 = Utf8               com/msxf/uds/uas/sdk/vo/ApplyCustContactVo
   #852 = NameAndType        #1215:#1021  // getEmergName:()Ljava/lang/String;
   #853 = NameAndType        #1216:#1096  // setContactName:(Ljava/lang/String;)V
   #854 = NameAndType        #1217:#1021  // getEmergRelation:()Ljava/lang/String;
   #855 = NameAndType        #576:#577    // parseContactRelation:(Ljava/lang/String;)Ljava/lang/String;
   #856 = NameAndType        #1218:#1096  // setContactRelation:(Ljava/lang/String;)V
   #857 = NameAndType        #1219:#1021  // getEmergTel:()Ljava/lang/String;
   #858 = NameAndType        #1220:#1096  // setContactMobile:(Ljava/lang/String;)V
   #859 = NameAndType        #1221:#1091  // add:(Ljava/lang/Object;)Z
   #860 = NameAndType        #1222:#1223  // setContactList:(Ljava/util/List;)V
   #861 = NameAndType        #438:#439    // areaService:Lcom/msxf/eyas/cms/sdk/service/BaseDicAreaRemoteService;
   #862 = Class              #1224        // com/msxf/eyas/cms/sdk/service/BaseDicAreaRemoteService
   #863 = NameAndType        #1225:#1226  // findAreaCodeByAreaName:(Ljava/lang/String;Z)Ljava/lang/String;
   #864 = NameAndType        #1227:#1096  // setAbodeState:(Ljava/lang/String;)V
   #865 = NameAndType        #1228:#1096  // setAbodeCity:(Ljava/lang/String;)V
   #866 = NameAndType        #1229:#1096  // setAbodeZone:(Ljava/lang/String;)V
   #867 = Utf8               com/msxf/vopen/dto/req/CreditAuthCodeReqDTO
   #868 = NameAndType        #1230:#1096  // setAppid:(Ljava/lang/String;)V
   #869 = NameAndType        #1231:#1096  // setUserPhone:(Ljava/lang/String;)V
   #870 = NameAndType        #1232:#1096  // setWhite:(Ljava/lang/String;)V
   #871 = Class              #1233        // com/msxf/vopen/constants/YONEnum
   #872 = NameAndType        #1234:#1235  // N:Lcom/msxf/vopen/constants/YONEnum;
   #873 = NameAndType        #1236:#1237  // setZhimaCredit:(Lcom/msxf/vopen/constants/YONEnum;)V
   #874 = Utf8               com/msxf/eyas/cmc/vo/user/UserMobileRegVo
   #875 = Class              #1238        // com/msxf/vopen/util/OpenUtil
   #876 = NameAndType        #1239:#1021  // generateLoginPassWord:()Ljava/lang/String;
   #877 = NameAndType        #1240:#1096  // setMobile:(Ljava/lang/String;)V
   #878 = Class              #1241        // com/msxf/vopen/util/SHAUtil
   #879 = NameAndType        #1242:#577   // encryptSHA256:(Ljava/lang/String;)Ljava/lang/String;
   #880 = NameAndType        #1243:#1096  // setPassword:(Ljava/lang/String;)V
   #881 = Utf8               com/msxf/eyas/cmc/vo/base/ApiApplicationVO
   #882 = Class              #1244        // com/msxf/eyas/common/util/BeanUtil
   #883 = NameAndType        #1245:#1246  // copyProperties:(Ljava/lang/Object;Ljava/lang/Class;)Ljava/lang/Object;
   #884 = NameAndType        #1247:#1248  // setApiApplication:(Lcom/msxf/eyas/cmc/vo/base/ApiApplicationVO;)V
   #885 = NameAndType        #1249:#1250  // getDeviceInfo:()Lcom/msxf/eyas/cmc/vo/base/DeviceInfo;
   #886 = Utf8               com/msxf/eyas/cmc/vo/base/DeviceInfo
   #887 = NameAndType        #1251:#1252  // setDeviceInfo:(Lcom/msxf/eyas/cmc/vo/base/DeviceInfo;)V
   #888 = Utf8               2099-12-30
   #889 = Utf8               java/lang/String
   #890 = Utf8               yyyy-MM-dd
   #891 = NameAndType        #1253:#1254  // parseDate:(Ljava/lang/String;[Ljava/lang/String;)Ljava/util/Date;
   #892 = Utf8               java/text/ParseException
   #893 = NameAndType        #1255:#446   // printStackTrace:()V
   #894 = Utf8               com/msxf/eyas/cmc/vo/cust/CustBaseInfoVO
   #895 = NameAndType        #1256:#1096  // setIdType:(Ljava/lang/String;)V
   #896 = Utf8               80010114
   #897 = NameAndType        #1257:#1096  // setCustSourceCooperator:(Ljava/lang/String;)V
   #898 = Utf8               vopen
   #899 = NameAndType        #1258:#1096  // setCustSourceTerm:(Ljava/lang/String;)V
   #900 = NameAndType        #1259:#1173  // setIdLastDate:(Ljava/util/Date;)V
   #901 = Utf8               com/msxf/eyas/cmc/vo/cust/CustOccupationInfoVO
   #902 = NameAndType        #1260:#1021  // getSchool:()Ljava/lang/String;
   #903 = Utf8               /
   #904 = NameAndType        #1261:#1021  // getUnitName:()Ljava/lang/String;
   #905 = NameAndType        #1262:#1096  // setUnitName:(Ljava/lang/String;)V
   #906 = NameAndType        #1263:#1021  // getWorkAddressProvince:()Ljava/lang/String;
   #907 = NameAndType        #1264:#1096  // setEmpProvince:(Ljava/lang/String;)V
   #908 = NameAndType        #1265:#1021  // getWorkAddressCity:()Ljava/lang/String;
   #909 = NameAndType        #1266:#1096  // setEmpCity:(Ljava/lang/String;)V
   #910 = NameAndType        #1267:#1021  // getWorkAddressArea:()Ljava/lang/String;
   #911 = NameAndType        #1268:#1096  // setEmpZone:(Ljava/lang/String;)V
   #912 = NameAndType        #1269:#1021  // getWorkAddressDetail:()Ljava/lang/String;
   #913 = NameAndType        #1270:#1096  // setEmpAddr:(Ljava/lang/String;)V
   #914 = NameAndType        #1271:#1021  // getUnitTel:()Ljava/lang/String;
   #915 = NameAndType        #1272:#1096  // setEmpPhone:(Ljava/lang/String;)V
   #916 = Utf8               com/msxf/eyas/cmc/vo/cust/CustContactVO
   #917 = Utf8               com/msxf/eyas/cmc/vo/cust/CustInfoVO
   #918 = NameAndType        #1273:#1274  // setBaseInfo:(Lcom/msxf/eyas/cmc/vo/cust/CustBaseInfoVO;)V
   #919 = NameAndType        #1275:#1276  // setOccupationInfo:(Lcom/msxf/eyas/cmc/vo/cust/CustOccupationInfoVO;)V
   #920 = NameAndType        #1277:#1054  // hashCode:()I
   #921 = Utf8               PARENT
   #922 = Utf8               SPOUSE
   #923 = Utf8               CHILDREN
   #924 = Utf8               KINSMAN
   #925 = Utf8               CLASSMATE
   #926 = Utf8               COLLEAGUE
   #927 = Utf8               FRIEND
   #928 = Class              #1278        // com/msxf/eyas/enums/ContactRelationTypeEnum
   #929 = NameAndType        #1279:#1280  // FATHER:Lcom/msxf/eyas/enums/ContactRelationTypeEnum;
   #930 = NameAndType        #1281:#1280  // CONSORT:Lcom/msxf/eyas/enums/ContactRelationTypeEnum;
   #931 = NameAndType        #1282:#1280  // CHILD:Lcom/msxf/eyas/enums/ContactRelationTypeEnum;
   #932 = NameAndType        #1283:#1280  // OTHER:Lcom/msxf/eyas/enums/ContactRelationTypeEnum;
   #933 = NameAndType        #1284:#1280  // SCHOOLMATE:Lcom/msxf/eyas/enums/ContactRelationTypeEnum;
   #934 = NameAndType        #926:#1280   // COLLEAGUE:Lcom/msxf/eyas/enums/ContactRelationTypeEnum;
   #935 = NameAndType        #927:#1280   // FRIEND:Lcom/msxf/eyas/enums/ContactRelationTypeEnum;
   #936 = NameAndType        #1285:#1021  // getContractNo:()Ljava/lang/String;
   #937 = Utf8               com/msxf/uds/uas/newsdk/sign/vo/CreateContractNoVo
   #938 = NameAndType        #1286:#1096  // setSysCode:(Ljava/lang/String;)V
   #939 = NameAndType        #429:#430    // signService:Lcom/msxf/uds/uas/newsdk/sign/service/ISignService;
   #940 = Class              #1287        // com/msxf/uds/uas/newsdk/sign/service/ISignService
   #941 = NameAndType        #579:#1288   // createContractNo:(Lcom/msxf/uds/uas/newsdk/sign/vo/CreateContractNoVo;)Ljava/lang/String;
   #942 = Utf8               com/msxf/vopen/entity/ThirdRelationEntity
   #943 = NameAndType        #1289:#1096  // setAppCode:(Ljava/lang/String;)V
   #944 = NameAndType        #1290:#1096  // setThirdApplyNo:(Ljava/lang/String;)V
   #945 = NameAndType        #1291:#1096  // setThirdProductCode:(Ljava/lang/String;)V
   #946 = NameAndType        #1292:#1096  // setThirdUserId:(Ljava/lang/String;)V
   #947 = Utf8               java/util/Date
   #948 = NameAndType        #1293:#1173  // setCreateTime:(Ljava/util/Date;)V
   #949 = Utf8               /upload/crpl_msjr/ocr/
   #950 = NameAndType        #1142:#1294  // append:(I)Ljava/lang/StringBuilder;
   #951 = Utf8               .txt
   #952 = NameAndType        #393:#394    // host:Ljava/lang/String;
   #953 = NameAndType        #399:#400    // port:Ljava/lang/Integer;
   #954 = NameAndType        #404:#394    // username:Ljava/lang/String;
   #955 = NameAndType        #402:#394    // secret:Ljava/lang/String;
   #956 = Class              #1295        // com/msxf/vopen/util/FtpUtil
   #957 = NameAndType        #1296:#1297  // downloadViaSFTP:(Ljava/lang/String;ILjava/lang/String;Ljava/lang/String;Ljava/lang/String;Ljava/lang/String;)Ljava/io/InputStream;
   #958 = Utf8               UTF-8
   #959 = Class              #1298        // org/apache/commons/io/Charsets
   #960 = NameAndType        #1299:#1300  // toCharset:(Ljava/lang/String;)Ljava/nio/charset/Charset;
   #961 = Class              #1301        // org/apache/commons/io/IOUtils
   #962 = NameAndType        #1144:#1302  // toString:(Ljava/io/InputStream;Ljava/nio/charset/Charset;)Ljava/lang/String;
   #963 = Utf8               com/msxf/vopen/exception/JdOcrException
   #964 = Class              #1303        // com/msxf/vopen/constants/CodeEnum
   #965 = NameAndType        #1304:#1305  // OCR_EXCEPTION:Lcom/msxf/vopen/constants/CodeEnum;
   #966 = Utf8               京东OCR文件流为空!
   #967 = NameAndType        #445:#1306   // "<init>":(ILjava/lang/String;)V
   #968 = NameAndType        #1307:#1021  // getSecretKey:()Ljava/lang/String;
   #969 = Class              #1308        // com/msxf/vopen/util/jd/DESUtil
   #970 = NameAndType        #1309:#1310  // decrypt2Byte:(Ljava/lang/String;Ljava/lang/String;)[B
   #971 = Utf8               java/io/ByteArrayInputStream
   #972 = NameAndType        #445:#1311   // "<init>":([B)V
   #973 = NameAndType        #411:#412    // ifsService:Lcom/msxf/eyas/ifs/IFSService;
   #974 = Utf8               141001
   #975 = NameAndType        #609:#610    // parseOCRCategory:(I)Ljava/lang/String;
   #976 = Utf8               jpg
   #977 = Class              #1312        // com/msxf/eyas/ifs/IFSService
   #978 = NameAndType        #1313:#1314  // upload:(Ljava/lang/String;Ljava/lang/String;Ljava/lang/String;Ljava/lang/String;Ljava/io/InputStream;)Ljava/lang/Long;
   #979 = Class              #1013        // java/lang/Long
   #980 = NameAndType        #1315:#1316  // longValue:()J
   #981 = Utf8               上传京东用户OCR信息成功,文件id:{}
   #982 = NameAndType        #1204:#1317  // valueOf:(J)Ljava/lang/Long;
   #983 = NameAndType        #1318:#1319  // info:(Ljava/lang/String;Ljava/lang/Object;)V
   #984 = NameAndType        #1204:#1320  // valueOf:(J)Ljava/lang/String;
   #985 = Class              #1321        // com/msxf/vopen/constants/IFSEnum
   #986 = NameAndType        #994:#1322   // F:Lcom/msxf/vopen/constants/IFSEnum;
   #987 = NameAndType        #1323:#1021  // name:()Ljava/lang/String;
   #988 = NameAndType        #995:#1322   // R:Lcom/msxf/vopen/constants/IFSEnum;
   #989 = NameAndType        #1324:#1322  // P:Lcom/msxf/vopen/constants/IFSEnum;
   #990 = Class              #1018        // java/io/InputStream
   #991 = NameAndType        #1325:#446   // close:()V
   #992 = NameAndType        #1326:#446   // logoutViaSFTP:()V
   #993 = NameAndType        #1327:#1328  // link:(Ljava/lang/String;Ljava/lang/String;Ljava/util/List;Ljava/util/List;)V
   #994 = Utf8               F
   #995 = Utf8               R
   #996 = Utf8               D
   #997 = Utf8               com/msxf/vopen/dto/req/jd/NotifyIOCRReqDTO
   #998 = Utf8               京东OCR请求参数:{}
   #999 = NameAndType        #1044:#1319  // warn:(Ljava/lang/String;Ljava/lang/Object;)V
  #1000 = Utf8               JD
  #1001 = NameAndType        #1329:#1039  // findByThirdUserId:(Ljava/lang/String;Ljava/lang/String;)Lcom/msxf/vopen/entity/ThirdRelationEntity;
  #1002 = Utf8               京东OCR请求的第三方用信息{}
  #1003 = Utf8               com/msxf/vopen/service/biz/impl/jd/JDApplyServiceImpl
  #1004 = Class              #1330        // org/slf4j/LoggerFactory
  #1005 = NameAndType        #1331:#1332  // getLogger:(Ljava/lang/Class;)Lorg/slf4j/Logger;
  #1006 = Utf8               com/msxf/vopen/service/biz/jd/JDApplyService
  #1007 = Utf8               com/msxf/vopen/dto/req/jd/CheckApplyReqDTO$UserInfoDTO
  #1008 = Utf8               com/msxf/vopen/dto/jd/CommonRequest
  #1009 = Utf8               com/msxf/vopen/support/ApiCaller
  #1010 = Utf8               com/msxf/vopen/entity/ChannelEntity
  #1011 = Utf8               com/msxf/vopen/constants/CommonResult
  #1012 = Utf8               com/msxf/eyas/cmc/vo/user/UserBaseInfoVO
  #1013 = Utf8               java/lang/Long
  #1014 = Utf8               com/msxf/eyas/cmc/vo/user/LoginResultVO
  #1015 = Utf8               com/msxf/uds/uas/sdk/vo/ApplyQueryDetailVo
  #1016 = Utf8               java/util/List
  #1017 = Utf8               java/util/Iterator
  #1018 = Utf8               java/io/InputStream
  #1019 = Utf8               java/lang/Throwable
  #1020 = Utf8               getRequestData
  #1021 = Utf8               ()Ljava/lang/String;
  #1022 = Utf8               com/alibaba/fastjson/JSONObject
  #1023 = Utf8               parseObject
  #1024 = Utf8               (Ljava/lang/String;Ljava/lang/Class;)Ljava/lang/Object;
  #1025 = Utf8               com/msxf/boot/core/util/log/BusinessLogger
  #1026 = Utf8               log
  #1027 = Utf8               (Ljava/lang/String;[Ljava/lang/Object;)V
  #1028 = Utf8               getUserInfo
  #1029 = Utf8               ()Lcom/msxf/vopen/dto/req/jd/CheckApplyReqDTO$UserInfoDTO;
  #1030 = Utf8               com/msxf/vopen/service/biz/BizHelpService
  #1031 = Utf8               getApiCaller
  #1032 = Utf8               (Ljava/lang/String;)Lcom/msxf/vopen/support/ApiCaller;
  #1033 = Utf8               com/msxf/vopen/service/AppBaseService
  #1034 = Utf8               getChannelInfo
  #1035 = Utf8               (Ljava/lang/String;)Lcom/msxf/vopen/entity/ChannelEntity;
  #1036 = Utf8               getApplyNo
  #1037 = Utf8               com/msxf/vopen/repository/ThirdRelationRepository
  #1038 = Utf8               findByThirdApplyNo
  #1039 = Utf8               (Ljava/lang/String;Ljava/lang/String;)Lcom/msxf/vopen/entity/ThirdRelationEntity;
  #1040 = Utf8               com/msxf/uds/uas/sdk/IApplicationService
  #1041 = Utf8               getUserId
  #1042 = Utf8               getMessage
  #1043 = Utf8               org/slf4j/Logger
  #1044 = Utf8               warn
  #1045 = Utf8               (Ljava/lang/String;Ljava/lang/Object;Ljava/lang/Object;)V
  #1046 = Utf8               com/msxf/vopen/constants/JDRespCodeEnum
  #1047 = Utf8               UNKNOWN_ERROR
  #1048 = Utf8               Lcom/msxf/vopen/constants/JDRespCodeEnum;
  #1049 = Utf8               (Lcom/msxf/vopen/constants/JDRespCodeEnum;Ljava/lang/String;)V
  #1050 = Utf8               com/msxf/vopen/service/biz/BizUserService
  #1051 = Utf8               getCreditAuthCode
  #1052 = Utf8               (Lcom/msxf/vopen/dto/req/CreditAuthCodeReqDTO;)Lcom/msxf/vopen/constants/CommonResult;
  #1053 = Utf8               getCode
  #1054 = Utf8               ()I
  #1055 = Utf8               com/alibaba/fastjson/JSON
  #1056 = Utf8               toJSONString
  #1057 = Utf8               (Ljava/lang/Object;)Ljava/lang/String;
  #1058 = Utf8               getData
  #1059 = Utf8               ()Ljava/lang/Object;
  #1060 = Utf8               getAuthCode
  #1061 = Utf8               getUsername
  #1062 = Utf8               getCertNo
  #1063 = Utf8               com/msxf/eyas/dsc/DSCService
  #1064 = Utf8               getUniqueId
  #1065 = Utf8               (Ljava/lang/String;Ljava/lang/String;)Ljava/lang/String;
  #1066 = Utf8               getUserTel
  #1067 = Utf8               com/msxf/eyas/cmc/sdk/user/IUserInfoQueryService
  #1068 = Utf8               getBaseUserInfoByMobile
  #1069 = Utf8               (Ljava/lang/String;)Lcom/msxf/eyas/cmc/vo/user/UserBaseInfoVO;
  #1070 = Utf8               com/msxf/eyas/cmc/sdk/user/IUserService
  #1071 = Utf8               mobileReg
  #1072 = Utf8               (Lcom/msxf/eyas/cmc/vo/user/UserMobileRegVo;)Lcom/msxf/eyas/cmc/vo/user/LoginResultVO;
  #1073 = Utf8               getMobile
  #1074 = Utf8               com/msxf/eyas/cmc/sdk/cust/ICustInfoService
  #1075 = Utf8               createCust
  #1076 = Utf8               (Lcom/msxf/eyas/cmc/vo/cust/CustInfoVO;)Lcom/msxf/eyas/cmc/vo/user/UserBaseInfoVO;
  #1077 = Utf8               ()Ljava/lang/Long;
  #1078 = Utf8               getYouqianTerminal
  #1079 = Utf8               getYouqianChannel
  #1080 = Utf8               com/msxf/vopen/service/biz/BizNotifyService
  #1081 = Utf8               notifyYouqianUserRecommendedInfo
  #1082 = Utf8               (Ljava/lang/Long;Ljava/lang/String;Ljava/lang/String;Ljava/lang/String;)V
  #1083 = Utf8               getId
  #1084 = Utf8               getRequestNo
  #1085 = Utf8               (Lcom/msxf/uds/uas/sdk/vo/ApplyVo;)Ljava/lang/String;
  #1086 = Utf8               com/msxf/uds/uas/exception/UASErrorCode
  #1087 = Utf8               APPLY_QUERY_SIGN_ORDER
  #1088 = Utf8               Lcom/msxf/uds/uas/exception/UASErrorCode;
  #1089 = Utf8               getErrorCode
  #1090 = Utf8               equals
  #1091 = Utf8               (Ljava/lang/Object;)Z
  #1092 = Utf8               (Lcom/msxf/vopen/dto/jd/CommonRequest;Lcom/msxf/vopen/constants/JDRespCodeEnum;)V
  #1093 = Utf8               save
  #1094 = Utf8               (Ljava/lang/Object;)Ljava/lang/Object;
  #1095 = Utf8               setApplyNo
  #1096 = Utf8               (Ljava/lang/String;)V
  #1097 = Utf8               getApplyDetail
  #1098 = Utf8               (Lcom/msxf/uds/uas/sdk/vo/ApplyQueryRequestVo;)Lcom/msxf/uds/uas/sdk/vo/ApplyQueryDetailVo;
  #1099 = Utf8               com/msxf/vopen/service/biz/jd/JDNotifyService
  #1100 = Utf8               syncNotifyDataPlatformRiskInfo
  #1101 = Utf8               (Lcom/msxf/vopen/dto/jd/CommonRequest;)V
  #1102 = Utf8               getAgreementTariffRate
  #1103 = Utf8               parseJdSvcfee
  #1104 = Utf8               EXPIRE_7DAY
  #1105 = Utf8               java/lang/Integer
  #1106 = Utf8               intValue
  #1107 = Utf8               getNotifyUrl
  #1108 = Utf8               redis/clients/jedis/JedisCluster
  #1109 = Utf8               setex
  #1110 = Utf8               (Ljava/lang/String;ILjava/lang/String;)Ljava/lang/String;
  #1111 = Utf8               SUCCESS
  #1112 = Utf8               (Lcom/msxf/vopen/dto/jd/CommonRequest;Lcom/msxf/vopen/constants/JDRespCodeEnum;Ljava/lang/String;)V
  #1113 = Utf8               setMhtApplyNo
  #1114 = Utf8               getStatus
  #1115 = Utf8               parseJDApplyStatus
  #1116 = Utf8               setCheckStatus
  #1117 = Utf8               getAccLmt
  #1118 = Utf8               ()Ljava/math/BigDecimal;
  #1119 = Utf8               parseCent
  #1120 = Utf8               (Ljava/math/BigDecimal;)Ljava/lang/String;
  #1121 = Utf8               setCheckAmount
  #1122 = Utf8               getApplyTime
  #1123 = Utf8               ()Ljava/util/Date;
  #1124 = Utf8               formatJdDate
  #1125 = Utf8               (Ljava/util/Date;)Ljava/lang/String;
  #1126 = Utf8               setCheckTime
  #1127 = Utf8               getApplyProduct
  #1128 = Utf8               setProductInfo
  #1129 = Utf8               (Lcom/msxf/vopen/dto/resp/jd/CheckApplyRespDTO$ProductInfoDTO;)V
  #1130 = Utf8               org/apache/commons/lang3/time/DateUtils
  #1131 = Utf8               addDays
  #1132 = Utf8               (Ljava/util/Date;I)Ljava/util/Date;
  #1133 = Utf8               setExpiryTime
  #1134 = Utf8               setProductId
  #1135 = Utf8               setInterestRate
  #1136 = Utf8               setSupportPeriod
  #1137 = Utf8               setEarlyRepayment
  #1138 = Utf8               setRepaymentMethod
  #1139 = Utf8               setPartialWithdraw
  #1140 = Utf8               setInterestsCalculation
  #1141 = Utf8               setOverdueInterestRate
  #1142 = Utf8               append
  #1143 = Utf8               (Ljava/lang/String;)Ljava/lang/StringBuilder;
  #1144 = Utf8               toString
  #1145 = Utf8               setFeeDesc
  #1146 = Utf8               setUserId
  #1147 = Utf8               (Ljava/lang/Long;)V
  #1148 = Utf8               setApplySerialNo
  #1149 = Utf8               setUniqueId
  #1150 = Utf8               setProductCode
  #1151 = Utf8               setSubTerminalType
  #1152 = Utf8               getApplication
  #1153 = Utf8               ()Lcom/msxf/vopen/support/ApiApplication;
  #1154 = Utf8               com/msxf/vopen/support/ApiApplication
  #1155 = Utf8               getCooperator
  #1156 = Utf8               setCooperatorId
  #1157 = Utf8               setLoanPurpose
  #1158 = Utf8               com/msxf/eyas/enums/LifeInsurancePlan
  #1159 = Utf8               NO
  #1160 = Utf8               Lcom/msxf/eyas/enums/LifeInsurancePlan;
  #1161 = Utf8               getStandardValue
  #1162 = Utf8               setJoinLifeInsurance
  #1163 = Utf8               com/msxf/vopen/constants/PrepayPkgEnum
  #1164 = Utf8               Lcom/msxf/vopen/constants/PrepayPkgEnum;
  #1165 = Utf8               setPrepayPkgInd
  #1166 = Utf8               setName
  #1167 = Utf8               com/msxf/vopen/util/StringUtil
  #1168 = Utf8               getGender
  #1169 = Utf8               setGender
  #1170 = Utf8               getBirth
  #1171 = Utf8               (Ljava/lang/String;)Ljava/util/Date;
  #1172 = Utf8               setBirth
  #1173 = Utf8               (Ljava/util/Date;)V
  #1174 = Utf8               setIdNo
  #1175 = Utf8               setCellphone
  #1176 = Utf8               setBankCardNo
  #1177 = Utf8               setEmail
  #1178 = Utf8               setEmpPost
  #1179 = Utf8               setEmpType
  #1180 = Utf8               setEmpStructure
  #1181 = Utf8               DEFAULT_MONTH_INCOME
  #1182 = Utf8               setMonthIncome
  #1183 = Utf8               getHomeAddressProvince
  #1184 = Utf8               setAbodeStateName
  #1185 = Utf8               getHomeAddressCity
  #1186 = Utf8               setAbodeCityName
  #1187 = Utf8               getHomeAddressArea
  #1188 = Utf8               setAbodeZoneName
  #1189 = Utf8               getHomeAddressDetail
  #1190 = Utf8               setAbodeDetail
  #1191 = Utf8               setCreditAuthSerialNo
  #1192 = Utf8               setBankName
  #1193 = Utf8               setBankCityName
  #1194 = Utf8               setBankProvinceName
  #1195 = Utf8               getApplyAmount
  #1196 = Utf8               org/apache/commons/lang3/StringUtils
  #1197 = Utf8               isEmpty
  #1198 = Utf8               (Ljava/lang/CharSequence;)Z
  #1199 = Utf8               parseYuan
  #1200 = Utf8               (Ljava/lang/String;)Ljava/math/BigDecimal;
  #1201 = Utf8               setApplyLmt
  #1202 = Utf8               (Ljava/math/BigDecimal;)V
  #1203 = Utf8               getApplyPeriod
  #1204 = Utf8               valueOf
  #1205 = Utf8               (Ljava/lang/String;)Ljava/lang/Integer;
  #1206 = Utf8               setApplyLoanTerm
  #1207 = Utf8               (Ljava/lang/Integer;)V
  #1208 = Utf8               getEmergList
  #1209 = Utf8               ()Ljava/util/List;
  #1210 = Utf8               iterator
  #1211 = Utf8               ()Ljava/util/Iterator;
  #1212 = Utf8               hasNext
  #1213 = Utf8               ()Z
  #1214 = Utf8               next
  #1215 = Utf8               getEmergName
  #1216 = Utf8               setContactName
  #1217 = Utf8               getEmergRelation
  #1218 = Utf8               setContactRelation
  #1219 = Utf8               getEmergTel
  #1220 = Utf8               setContactMobile
  #1221 = Utf8               add
  #1222 = Utf8               setContactList
  #1223 = Utf8               (Ljava/util/List;)V
  #1224 = Utf8               com/msxf/eyas/cms/sdk/service/BaseDicAreaRemoteService
  #1225 = Utf8               findAreaCodeByAreaName
  #1226 = Utf8               (Ljava/lang/String;Z)Ljava/lang/String;
  #1227 = Utf8               setAbodeState
  #1228 = Utf8               setAbodeCity
  #1229 = Utf8               setAbodeZone
  #1230 = Utf8               setAppid
  #1231 = Utf8               setUserPhone
  #1232 = Utf8               setWhite
  #1233 = Utf8               com/msxf/vopen/constants/YONEnum
  #1234 = Utf8               N
  #1235 = Utf8               Lcom/msxf/vopen/constants/YONEnum;
  #1236 = Utf8               setZhimaCredit
  #1237 = Utf8               (Lcom/msxf/vopen/constants/YONEnum;)V
  #1238 = Utf8               com/msxf/vopen/util/OpenUtil
  #1239 = Utf8               generateLoginPassWord
  #1240 = Utf8               setMobile
  #1241 = Utf8               com/msxf/vopen/util/SHAUtil
  #1242 = Utf8               encryptSHA256
  #1243 = Utf8               setPassword
  #1244 = Utf8               com/msxf/eyas/common/util/BeanUtil
  #1245 = Utf8               copyProperties
  #1246 = Utf8               (Ljava/lang/Object;Ljava/lang/Class;)Ljava/lang/Object;
  #1247 = Utf8               setApiApplication
  #1248 = Utf8               (Lcom/msxf/eyas/cmc/vo/base/ApiApplicationVO;)V
  #1249 = Utf8               getDeviceInfo
  #1250 = Utf8               ()Lcom/msxf/eyas/cmc/vo/base/DeviceInfo;
  #1251 = Utf8               setDeviceInfo
  #1252 = Utf8               (Lcom/msxf/eyas/cmc/vo/base/DeviceInfo;)V
  #1253 = Utf8               parseDate
  #1254 = Utf8               (Ljava/lang/String;[Ljava/lang/String;)Ljava/util/Date;
  #1255 = Utf8               printStackTrace
  #1256 = Utf8               setIdType
  #1257 = Utf8               setCustSourceCooperator
  #1258 = Utf8               setCustSourceTerm
  #1259 = Utf8               setIdLastDate
  #1260 = Utf8               getSchool
  #1261 = Utf8               getUnitName
  #1262 = Utf8               setUnitName
  #1263 = Utf8               getWorkAddressProvince
  #1264 = Utf8               setEmpProvince
  #1265 = Utf8               getWorkAddressCity
  #1266 = Utf8               setEmpCity
  #1267 = Utf8               getWorkAddressArea
  #1268 = Utf8               setEmpZone
  #1269 = Utf8               getWorkAddressDetail
  #1270 = Utf8               setEmpAddr
  #1271 = Utf8               getUnitTel
  #1272 = Utf8               setEmpPhone
  #1273 = Utf8               setBaseInfo
  #1274 = Utf8               (Lcom/msxf/eyas/cmc/vo/cust/CustBaseInfoVO;)V
  #1275 = Utf8               setOccupationInfo
  #1276 = Utf8               (Lcom/msxf/eyas/cmc/vo/cust/CustOccupationInfoVO;)V
  #1277 = Utf8               hashCode
  #1278 = Utf8               com/msxf/eyas/enums/ContactRelationTypeEnum
  #1279 = Utf8               FATHER
  #1280 = Utf8               Lcom/msxf/eyas/enums/ContactRelationTypeEnum;
  #1281 = Utf8               CONSORT
  #1282 = Utf8               CHILD
  #1283 = Utf8               OTHER
  #1284 = Utf8               SCHOOLMATE
  #1285 = Utf8               getContractNo
  #1286 = Utf8               setSysCode
  #1287 = Utf8               com/msxf/uds/uas/newsdk/sign/service/ISignService
  #1288 = Utf8               (Lcom/msxf/uds/uas/newsdk/sign/vo/CreateContractNoVo;)Ljava/lang/String;
  #1289 = Utf8               setAppCode
  #1290 = Utf8               setThirdApplyNo
  #1291 = Utf8               setThirdProductCode
  #1292 = Utf8               setThirdUserId
  #1293 = Utf8               setCreateTime
  #1294 = Utf8               (I)Ljava/lang/StringBuilder;
  #1295 = Utf8               com/msxf/vopen/util/FtpUtil
  #1296 = Utf8               downloadViaSFTP
  #1297 = Utf8               (Ljava/lang/String;ILjava/lang/String;Ljava/lang/String;Ljava/lang/String;Ljava/lang/String;)Ljava/io/InputStream;
  #1298 = Utf8               org/apache/commons/io/Charsets
  #1299 = Utf8               toCharset
  #1300 = Utf8               (Ljava/lang/String;)Ljava/nio/charset/Charset;
  #1301 = Utf8               org/apache/commons/io/IOUtils
  #1302 = Utf8               (Ljava/io/InputStream;Ljava/nio/charset/Charset;)Ljava/lang/String;
  #1303 = Utf8               com/msxf/vopen/constants/CodeEnum
  #1304 = Utf8               OCR_EXCEPTION
  #1305 = Utf8               Lcom/msxf/vopen/constants/CodeEnum;
  #1306 = Utf8               (ILjava/lang/String;)V
  #1307 = Utf8               getSecretKey
  #1308 = Utf8               com/msxf/vopen/util/jd/DESUtil
  #1309 = Utf8               decrypt2Byte
  #1310 = Utf8               (Ljava/lang/String;Ljava/lang/String;)[B
  #1311 = Utf8               ([B)V
  #1312 = Utf8               com/msxf/eyas/ifs/IFSService
  #1313 = Utf8               upload
  #1314 = Utf8               (Ljava/lang/String;Ljava/lang/String;Ljava/lang/String;Ljava/lang/String;Ljava/io/InputStream;)Ljava/lang/Long;
  #1315 = Utf8               longValue
  #1316 = Utf8               ()J
  #1317 = Utf8               (J)Ljava/lang/Long;
  #1318 = Utf8               info
  #1319 = Utf8               (Ljava/lang/String;Ljava/lang/Object;)V
  #1320 = Utf8               (J)Ljava/lang/String;
  #1321 = Utf8               com/msxf/vopen/constants/IFSEnum
  #1322 = Utf8               Lcom/msxf/vopen/constants/IFSEnum;
  #1323 = Utf8               name
  #1324 = Utf8               P
  #1325 = Utf8               close
  #1326 = Utf8               logoutViaSFTP
  #1327 = Utf8               link
  #1328 = Utf8               (Ljava/lang/String;Ljava/lang/String;Ljava/util/List;Ljava/util/List;)V
  #1329 = Utf8               findByThirdUserId
  #1330 = Utf8               org/slf4j/LoggerFactory
  #1331 = Utf8               getLogger
  #1332 = Utf8               (Ljava/lang/Class;)Lorg/slf4j/Logger;
{
  public com.msxf.vopen.service.biz.impl.jd.JDApplyServiceImpl();
    descriptor: ()V
    flags: ACC_PUBLIC
    Code:
      stack=1, locals=1, args_size=1
         0: aload_0
         1: invokespecial #2                  // Method java/lang/Object."<init>":()V
         4: return
      LineNumberTable:
        line 75: 0
      LocalVariableTable:
        Start  Length  Slot  Name   Signature
            0       5     0  this   Lcom/msxf/vopen/service/biz/impl/jd/JDApplyServiceImpl;

  public com.msxf.vopen.dto.jd.CommonResponse checkApply(com.msxf.vopen.dto.jd.CommonRequest) throws java.lang.Exception;
    descriptor: (Lcom/msxf/vopen/dto/jd/CommonRequest;)Lcom/msxf/vopen/dto/jd/CommonResponse;
    flags: ACC_PUBLIC
    Code:
      stack=8, locals=19, args_size=2
         0: aload_1
         1: invokevirtual #3                  // Method com/msxf/vopen/dto/jd/CommonRequest.getRequestData:()Ljava/lang/String;
         4: ldc           #4                  // class com/msxf/vopen/dto/req/jd/CheckApplyReqDTO
         6: invokestatic  #5                  // Method com/alibaba/fastjson/JSONObject.parseObject:(Ljava/lang/String;Ljava/lang/Class;)Ljava/lang/Object;
         9: checkcast     #4                  // class com/msxf/vopen/dto/req/jd/CheckApplyReqDTO
        12: astore_2
        13: ldc           #6                  // String 统计各合作方提交申请次数
        15: iconst_2
        16: anewarray     #7                  // class java/lang/Object
        19: dup
        20: iconst_0
        21: ldc           #8                  // String 授信申请来自合作方
        23: aastore
        24: dup
        25: iconst_1
        26: ldc           #9                  // String jd
        28: aastore
        29: invokestatic  #10                 // Method com/msxf/boot/core/util/log/BusinessLogger.log:(Ljava/lang/String;[Ljava/lang/Object;)V
        32: aload_2
        33: invokevirtual #11                 // Method com/msxf/vopen/dto/req/jd/CheckApplyReqDTO.getUserInfo:()Lcom/msxf/vopen/dto/req/jd/CheckApplyReqDTO$UserInfoDTO;
        36: astore_3
        37: aload_0
        38: getfield      #12                 // Field bizHelpService:Lcom/msxf/vopen/service/biz/BizHelpService;
        41: ldc           #9                  // String jd
        43: invokeinterface #13,  2           // InterfaceMethod com/msxf/vopen/service/biz/BizHelpService.getApiCaller:(Ljava/lang/String;)Lcom/msxf/vopen/support/ApiCaller;
        48: astore        4
        50: aload_0
        51: getfield      #14                 // Field appBaseService:Lcom/msxf/vopen/service/AppBaseService;
        54: ldc           #9                  // String jd
        56: invokevirtual #15                 // Method com/msxf/vopen/service/AppBaseService.getChannelInfo:(Ljava/lang/String;)Lcom/msxf/vopen/entity/ChannelEntity;
        59: astore        5
        61: ldc           #16                 // String
        63: astore        6
        65: ldc           #16                 // String
        67: astore        7
        69: aload_0
        70: getfield      #17                 // Field jdUserDao:Lcom/msxf/vopen/repository/ThirdRelationRepository;
        73: ldc           #9                  // String jd
        75: aload_2
        76: invokevirtual #18                 // Method com/msxf/vopen/dto/req/jd/CheckApplyReqDTO.getApplyNo:()Ljava/lang/String;
        79: invokeinterface #19,  3           // InterfaceMethod com/msxf/vopen/repository/ThirdRelationRepository.findByThirdApplyNo:(Ljava/lang/String;Ljava/lang/String;)Lcom/msxf/vopen/entity/ThirdRelationEntity;
        84: astore        8
        86: aload         8
        88: ifnonnull     628
        91: aload_0
        92: getfield      #20                 // Field iApplicationService:Lcom/msxf/uds/uas/sdk/IApplicationService;
        95: invokeinterface #21,  1           // InterfaceMethod com/msxf/uds/uas/sdk/IApplicationService.getApplyNo:()Ljava/lang/String;
       100: astore        6
       102: aload_0
       103: aload_3
       104: invokevirtual #22                 // Method com/msxf/vopen/dto/req/jd/CheckApplyReqDTO$UserInfoDTO.getUserId:()Ljava/lang/String;
       107: aload         6
       109: invokevirtual #23                 // Method uploadJDUserOCRInfo:(Ljava/lang/String;Ljava/lang/String;)V
       112: goto          147
       115: astore        9
       117: getstatic     #25                 // Field logger:Lorg/slf4j/Logger;
       120: ldc           #26                 // String 京东OCR用户信息拉取上传异常：[{}]
       122: aload         9
       124: invokevirtual #27                 // Method java/lang/Exception.getMessage:()Ljava/lang/String;
       127: aload         9
       129: invokeinterface #28,  4           // InterfaceMethod org/slf4j/Logger.warn:(Ljava/lang/String;Ljava/lang/Object;Ljava/lang/Object;)V
       134: new           #29                 // class com/msxf/vopen/dto/jd/CommonResponse
       137: dup
       138: getstatic     #30                 // Field com/msxf/vopen/constants/JDRespCodeEnum.UNKNOWN_ERROR:Lcom/msxf/vopen/constants/JDRespCodeEnum;
       141: ldc           #31                 // String OCR拉取/上传异常
       143: invokespecial #32                 // Method com/msxf/vopen/dto/jd/CommonResponse."<init>":(Lcom/msxf/vopen/constants/JDRespCodeEnum;Ljava/lang/String;)V
       146: areturn
       147: aload_0
       148: getfield      #33                 // Field bizUserService:Lcom/msxf/vopen/service/biz/BizUserService;
       151: aload_0
       152: aload_3
       153: invokespecial #34                 // Method getAuthCodeReqParams:(Lcom/msxf/vopen/dto/req/jd/CheckApplyReqDTO$UserInfoDTO;)Lcom/msxf/vopen/dto/req/CreditAuthCodeReqDTO;
       156: invokeinterface #35,  2           // InterfaceMethod com/msxf/vopen/service/biz/BizUserService.getCreditAuthCode:(Lcom/msxf/vopen/dto/req/CreditAuthCodeReqDTO;)Lcom/msxf/vopen/constants/CommonResult;
       161: astore        9
       163: aload         9
       165: invokevirtual #36                 // Method com/msxf/vopen/constants/CommonResult.getCode:()I
       168: ifeq          214
       171: aload_0
       172: aload_3
       173: invokespecial #34                 // Method getAuthCodeReqParams:(Lcom/msxf/vopen/dto/req/jd/CheckApplyReqDTO$UserInfoDTO;)Lcom/msxf/vopen/dto/req/CreditAuthCodeReqDTO;
       176: invokestatic  #37                 // Method com/alibaba/fastjson/JSON.toJSONString:(Ljava/lang/Object;)Ljava/lang/String;
       179: astore        10
       181: getstatic     #25                 // Field logger:Lorg/slf4j/Logger;
       184: ldc           #38                 // String 京东异常:获取征信授权码异常:{},请求参数:[{}]
       186: aload         9
       188: invokevirtual #39                 // Method com/msxf/vopen/constants/CommonResult.getMessage:()Ljava/lang/String;
       191: aload         10
       193: invokeinterface #28,  4           // InterfaceMethod org/slf4j/Logger.warn:(Ljava/lang/String;Ljava/lang/Object;Ljava/lang/Object;)V
       198: new           #29                 // class com/msxf/vopen/dto/jd/CommonResponse
       201: dup
       202: getstatic     #30                 // Field com/msxf/vopen/constants/JDRespCodeEnum.UNKNOWN_ERROR:Lcom/msxf/vopen/constants/JDRespCodeEnum;
       205: aload         9
       207: invokevirtual #39                 // Method com/msxf/vopen/constants/CommonResult.getMessage:()Ljava/lang/String;
       210: invokespecial #32                 // Method com/msxf/vopen/dto/jd/CommonResponse."<init>":(Lcom/msxf/vopen/constants/JDRespCodeEnum;Ljava/lang/String;)V
       213: areturn
       214: aload         9
       216: invokevirtual #40                 // Method com/msxf/vopen/constants/CommonResult.getData:()Ljava/lang/Object;
       219: checkcast     #41                 // class com/msxf/vopen/dto/resp/CreditAuthCodeRespDTO
       222: astore        10
       224: aload         10
       226: invokevirtual #42                 // Method com/msxf/vopen/dto/resp/CreditAuthCodeRespDTO.getAuthCode:()Ljava/lang/String;
       229: astore        11
       231: aload_0
       232: getfield      #43                 // Field dscService:Lcom/msxf/eyas/dsc/DSCService;
       235: aload_2
       236: invokevirtual #11                 // Method com/msxf/vopen/dto/req/jd/CheckApplyReqDTO.getUserInfo:()Lcom/msxf/vopen/dto/req/jd/CheckApplyReqDTO$UserInfoDTO;
       239: invokevirtual #44                 // Method com/msxf/vopen/dto/req/jd/CheckApplyReqDTO$UserInfoDTO.getUsername:()Ljava/lang/String;
       242: aload_2
       243: invokevirtual #11                 // Method com/msxf/vopen/dto/req/jd/CheckApplyReqDTO.getUserInfo:()Lcom/msxf/vopen/dto/req/jd/CheckApplyReqDTO$UserInfoDTO;
       246: invokevirtual #45                 // Method com/msxf/vopen/dto/req/jd/CheckApplyReqDTO$UserInfoDTO.getCertNo:()Ljava/lang/String;
       249: invokeinterface #46,  3           // InterfaceMethod com/msxf/eyas/dsc/DSCService.getUniqueId:(Ljava/lang/String;Ljava/lang/String;)Ljava/lang/String;
       254: astore        12
       256: aload_0
       257: getfield      #47                 // Field userInfoQueryService:Lcom/msxf/eyas/cmc/sdk/user/IUserInfoQueryService;
       260: aload_3
       261: invokevirtual #48                 // Method com/msxf/vopen/dto/req/jd/CheckApplyReqDTO$UserInfoDTO.getUserTel:()Ljava/lang/String;
       264: invokeinterface #49,  2           // InterfaceMethod com/msxf/eyas/cmc/sdk/user/IUserInfoQueryService.getBaseUserInfoByMobile:(Ljava/lang/String;)Lcom/msxf/eyas/cmc/vo/user/UserBaseInfoVO;
       269: astore        13
       271: aconst_null
       272: astore        14
       274: aload         13
       276: ifnonnull     446
       279: aload_0
       280: aload_3
       281: aload         4
       283: invokespecial #50                 // Method mobileRegParams:(Lcom/msxf/vopen/dto/req/jd/CheckApplyReqDTO$UserInfoDTO;Lcom/msxf/vopen/support/ApiCaller;)Lcom/msxf/eyas/cmc/vo/user/UserMobileRegVo;
       286: astore        15
       288: aconst_null
       289: astore        16
       291: aload_0
       292: getfield      #51                 // Field cmcUserService:Lcom/msxf/eyas/cmc/sdk/user/IUserService;
       295: aload         15
       297: invokeinterface #52,  2           // InterfaceMethod com/msxf/eyas/cmc/sdk/user/IUserService.mobileReg:(Lcom/msxf/eyas/cmc/vo/user/UserMobileRegVo;)Lcom/msxf/eyas/cmc/vo/user/LoginResultVO;
       302: astore        16
       304: goto          345
       307: astore        17
       309: getstatic     #25                 // Field logger:Lorg/slf4j/Logger;
       312: ldc           #54                 // String 京东异常:手机号注册异常:{},手机号:{}
       314: aload         17
       316: invokevirtual #55                 // Method com/msxf/eyas/cmc/CMCException.getMessage:()Ljava/lang/String;
       319: aload         15
       321: invokevirtual #56                 // Method com/msxf/eyas/cmc/vo/user/UserMobileRegVo.getMobile:()Ljava/lang/String;
       324: invokeinterface #28,  4           // InterfaceMethod org/slf4j/Logger.warn:(Ljava/lang/String;Ljava/lang/Object;Ljava/lang/Object;)V
       329: new           #29                 // class com/msxf/vopen/dto/jd/CommonResponse
       332: dup
       333: getstatic     #30                 // Field com/msxf/vopen/constants/JDRespCodeEnum.UNKNOWN_ERROR:Lcom/msxf/vopen/constants/JDRespCodeEnum;
       336: aload         17
       338: invokevirtual #55                 // Method com/msxf/eyas/cmc/CMCException.getMessage:()Ljava/lang/String;
       341: invokespecial #32                 // Method com/msxf/vopen/dto/jd/CommonResponse."<init>":(Lcom/msxf/vopen/constants/JDRespCodeEnum;Ljava/lang/String;)V
       344: areturn
       345: aload_0
       346: aload_2
       347: aload         12
       349: invokespecial #57                 // Method createCustParams:(Lcom/msxf/vopen/dto/req/jd/CheckApplyReqDTO;Ljava/lang/String;)Lcom/msxf/eyas/cmc/vo/cust/CustInfoVO;
       352: astore        17
       354: aload_0
       355: getfield      #58                 // Field iCustInfoService:Lcom/msxf/eyas/cmc/sdk/cust/ICustInfoService;
       358: aload         17
       360: invokeinterface #59,  2           // InterfaceMethod com/msxf/eyas/cmc/sdk/cust/ICustInfoService.createCust:(Lcom/msxf/eyas/cmc/vo/cust/CustInfoVO;)Lcom/msxf/eyas/cmc/vo/user/UserBaseInfoVO;
       365: pop
       366: goto          407
       369: astore        18
       371: getstatic     #25                 // Field logger:Lorg/slf4j/Logger;
       374: ldc           #60                 // String 京东异常:创建客户异常:{},UUID:{}
       376: aload         18
       378: invokevirtual #55                 // Method com/msxf/eyas/cmc/CMCException.getMessage:()Ljava/lang/String;
       381: aload         17
       383: invokevirtual #61                 // Method com/msxf/eyas/cmc/vo/cust/CustInfoVO.getUniqueId:()Ljava/lang/String;
       386: invokeinterface #28,  4           // InterfaceMethod org/slf4j/Logger.warn:(Ljava/lang/String;Ljava/lang/Object;Ljava/lang/Object;)V
       391: new           #29                 // class com/msxf/vopen/dto/jd/CommonResponse
       394: dup
       395: getstatic     #30                 // Field com/msxf/vopen/constants/JDRespCodeEnum.UNKNOWN_ERROR:Lcom/msxf/vopen/constants/JDRespCodeEnum;
       398: aload         18
       400: invokevirtual #55                 // Method com/msxf/eyas/cmc/CMCException.getMessage:()Ljava/lang/String;
       403: invokespecial #32                 // Method com/msxf/vopen/dto/jd/CommonResponse."<init>":(Lcom/msxf/vopen/constants/JDRespCodeEnum;Ljava/lang/String;)V
       406: areturn
       407: aload_0
       408: getfield      #62                 // Field bizNotifyService:Lcom/msxf/vopen/service/biz/BizNotifyService;
       411: aload         16
       413: invokevirtual #63                 // Method com/msxf/eyas/cmc/vo/user/LoginResultVO.getUserId:()Ljava/lang/Long;
       416: aload         5
       418: invokevirtual #64                 // Method com/msxf/vopen/entity/ChannelEntity.getCode:()Ljava/lang/String;
       421: aload         5
       423: invokevirtual #65                 // Method com/msxf/vopen/entity/ChannelEntity.getYouqianTerminal:()Ljava/lang/String;
       426: aload         5
       428: invokevirtual #66                 // Method com/msxf/vopen/entity/ChannelEntity.getYouqianChannel:()Ljava/lang/String;
       431: invokeinterface #67,  5           // InterfaceMethod com/msxf/vopen/service/biz/BizNotifyService.notifyYouqianUserRecommendedInfo:(Ljava/lang/Long;Ljava/lang/String;Ljava/lang/String;Ljava/lang/String;)V
       436: aload         16
       438: invokevirtual #63                 // Method com/msxf/eyas/cmc/vo/user/LoginResultVO.getUserId:()Ljava/lang/Long;
       441: astore        14
       443: goto          453
       446: aload         13
       448: invokevirtual #68                 // Method com/msxf/eyas/cmc/vo/user/UserBaseInfoVO.getId:()Ljava/lang/Long;
       451: astore        14
       453: aload_0
       454: aload_2
       455: aload         12
       457: aload         4
       459: aload         11
       461: aload         6
       463: aload_1
       464: invokevirtual #69                 // Method com/msxf/vopen/dto/jd/CommonRequest.getRequestNo:()Ljava/lang/String;
       467: aload         14
       469: invokespecial #70                 // Method getApplyVo:(Lcom/msxf/vopen/dto/req/jd/CheckApplyReqDTO;Ljava/lang/String;Lcom/msxf/vopen/support/ApiCaller;Ljava/lang/String;Ljava/lang/String;Ljava/lang/String;Ljava/lang/Long;)Lcom/msxf/uds/uas/sdk/vo/ApplyVo;
       472: astore        15
       474: aload_0
       475: getfield      #20                 // Field iApplicationService:Lcom/msxf/uds/uas/sdk/IApplicationService;
       478: aload         15
       480: invokeinterface #71,  2           // InterfaceMethod com/msxf/uds/uas/sdk/IApplicationService.apply:(Lcom/msxf/uds/uas/sdk/vo/ApplyVo;)Ljava/lang/String;
       485: pop
       486: goto          553
       489: astore        16
       491: getstatic     #25                 // Field logger:Lorg/slf4j/Logger;
       494: ldc           #73                 // String 京东异常:提交申请单异常:{},申请单号:{}
       496: aload         16
       498: invokevirtual #74                 // Method com/msxf/uds/uas/exception/UASException.getMessage:()Ljava/lang/String;
       501: aload         6
       503: invokeinterface #28,  4           // InterfaceMethod org/slf4j/Logger.warn:(Ljava/lang/String;Ljava/lang/Object;Ljava/lang/Object;)V
       508: getstatic     #75                 // Field com/msxf/uds/uas/exception/UASErrorCode.APPLY_QUERY_SIGN_ORDER:Lcom/msxf/uds/uas/exception/UASErrorCode;
       511: invokevirtual #76                 // Method com/msxf/uds/uas/exception/UASErrorCode.getCode:()Ljava/lang/String;
       514: aload         16
       516: invokevirtual #77                 // Method com/msxf/uds/uas/exception/UASException.getErrorCode:()Ljava/lang/String;
       519: invokevirtual #78                 // Method java/lang/String.equals:(Ljava/lang/Object;)Z
       522: ifeq          537
       525: new           #29                 // class com/msxf/vopen/dto/jd/CommonResponse
       528: dup
       529: aload_1
       530: getstatic     #79                 // Field com/msxf/vopen/constants/JDRespCodeEnum.APPLY_QUERY_SIGN_ORDER:Lcom/msxf/vopen/constants/JDRespCodeEnum;
       533: invokespecial #80                 // Method com/msxf/vopen/dto/jd/CommonResponse."<init>":(Lcom/msxf/vopen/dto/jd/CommonRequest;Lcom/msxf/vopen/constants/JDRespCodeEnum;)V
       536: areturn
       537: new           #29                 // class com/msxf/vopen/dto/jd/CommonResponse
       540: dup
       541: getstatic     #30                 // Field com/msxf/vopen/constants/JDRespCodeEnum.UNKNOWN_ERROR:Lcom/msxf/vopen/constants/JDRespCodeEnum;
       544: aload         16
       546: invokevirtual #74                 // Method com/msxf/uds/uas/exception/UASException.getMessage:()Ljava/lang/String;
       549: invokespecial #32                 // Method com/msxf/vopen/dto/jd/CommonResponse."<init>":(Lcom/msxf/vopen/constants/JDRespCodeEnum;Ljava/lang/String;)V
       552: areturn
       553: aload_0
       554: getfield      #17                 // Field jdUserDao:Lcom/msxf/vopen/repository/ThirdRelationRepository;
       557: aload_0
       558: aload_2
       559: aload         6
       561: aload         12
       563: invokespecial #81                 // Method saveJDUserInfo:(Lcom/msxf/vopen/dto/req/jd/CheckApplyReqDTO;Ljava/lang/String;Ljava/lang/String;)Lcom/msxf/vopen/entity/ThirdRelationEntity;
       566: invokeinterface #82,  2           // InterfaceMethod com/msxf/vopen/repository/ThirdRelationRepository.save:(Ljava/lang/Object;)Ljava/lang/Object;
       571: pop
       572: new           #83                 // class com/msxf/uds/uas/sdk/vo/ApplyQueryRequestVo
       575: dup
       576: invokespecial #84                 // Method com/msxf/uds/uas/sdk/vo/ApplyQueryRequestVo."<init>":()V
       579: astore        16
       581: aload         16
       583: aload         6
       585: invokevirtual #85                 // Method com/msxf/uds/uas/sdk/vo/ApplyQueryRequestVo.setApplyNo:(Ljava/lang/String;)V
       588: aload_0
       589: getfield      #20                 // Field iApplicationService:Lcom/msxf/uds/uas/sdk/IApplicationService;
       592: aload         16
       594: invokeinterface #86,  2           // InterfaceMethod com/msxf/uds/uas/sdk/IApplicationService.getApplyDetail:(Lcom/msxf/uds/uas/sdk/vo/ApplyQueryRequestVo;)Lcom/msxf/uds/uas/sdk/vo/ApplyQueryDetailVo;
       599: astore        17
       601: aload_0
       602: getfield      #87                 // Field jdNotifyService:Lcom/msxf/vopen/service/biz/jd/JDNotifyService;
       605: aload_1
       606: invokeinterface #88,  2           // InterfaceMethod com/msxf/vopen/service/biz/jd/JDNotifyService.syncNotifyDataPlatformRiskInfo:(Lcom/msxf/vopen/dto/jd/CommonRequest;)V
       611: aload_0
       612: getfield      #89                 // Field commonUtil:Lcom/msxf/vopen/util/jd/JDCommonUtil;
       615: aload         17
       617: invokevirtual #90                 // Method com/msxf/uds/uas/sdk/vo/ApplyQueryDetailVo.getAgreementTariffRate:()Ljava/lang/String;
       620: invokevirtual #91                 // Method com/msxf/vopen/util/jd/JDCommonUtil.parseJdSvcfee:(Ljava/lang/String;)Ljava/lang/String;
       623: astore        7
       625: goto          678
       628: aload         8
       630: invokevirtual #92                 // Method com/msxf/vopen/entity/ThirdRelationEntity.getApplyNo:()Ljava/lang/String;
       633: astore        6
       635: new           #83                 // class com/msxf/uds/uas/sdk/vo/ApplyQueryRequestVo
       638: dup
       639: invokespecial #84                 // Method com/msxf/uds/uas/sdk/vo/ApplyQueryRequestVo."<init>":()V
       642: astore        9
       644: aload         9
       646: aload         6
       648: invokevirtual #85                 // Method com/msxf/uds/uas/sdk/vo/ApplyQueryRequestVo.setApplyNo:(Ljava/lang/String;)V
       651: aload_0
       652: getfield      #20                 // Field iApplicationService:Lcom/msxf/uds/uas/sdk/IApplicationService;
       655: aload         9
       657: invokeinterface #86,  2           // InterfaceMethod com/msxf/uds/uas/sdk/IApplicationService.getApplyDetail:(Lcom/msxf/uds/uas/sdk/vo/ApplyQueryRequestVo;)Lcom/msxf/uds/uas/sdk/vo/ApplyQueryDetailVo;
       662: astore        10
       664: aload_0
       665: getfield      #89                 // Field commonUtil:Lcom/msxf/vopen/util/jd/JDCommonUtil;
       668: aload         10
       670: invokevirtual #90                 // Method com/msxf/uds/uas/sdk/vo/ApplyQueryDetailVo.getAgreementTariffRate:()Ljava/lang/String;
       673: invokevirtual #91                 // Method com/msxf/vopen/util/jd/JDCommonUtil.parseJdSvcfee:(Ljava/lang/String;)Ljava/lang/String;
       676: astore        7
       678: aload_0
       679: getfield      #93                 // Field redis:Lredis/clients/jedis/JedisCluster;
       682: ldc           #95                 // String vopen_jd_notify_apply
       684: getstatic     #96                 // Field com/msxf/vopen/constants/RedisConstants.EXPIRE_7DAY:Ljava/lang/Integer;
       687: invokevirtual #97                 // Method java/lang/Integer.intValue:()I
       690: aload_2
       691: invokevirtual #98                 // Method com/msxf/vopen/dto/req/jd/CheckApplyReqDTO.getNotifyUrl:()Ljava/lang/String;
       694: invokevirtual #99                 // Method redis/clients/jedis/JedisCluster.setex:(Ljava/lang/String;ILjava/lang/String;)Ljava/lang/String;
       697: pop
       698: new           #29                 // class com/msxf/vopen/dto/jd/CommonResponse
       701: dup
       702: aload_1
       703: getstatic     #100                // Field com/msxf/vopen/constants/JDRespCodeEnum.SUCCESS:Lcom/msxf/vopen/constants/JDRespCodeEnum;
       706: aload_0
       707: aload         6
       709: aload_2
       710: aload         7
       712: invokespecial #101                // Method jdResp:(Ljava/lang/String;Lcom/msxf/vopen/dto/req/jd/CheckApplyReqDTO;Ljava/lang/String;)Lcom/msxf/vopen/dto/resp/jd/CheckApplyRespDTO;
       715: invokestatic  #37                 // Method com/alibaba/fastjson/JSON.toJSONString:(Ljava/lang/Object;)Ljava/lang/String;
       718: invokespecial #102                // Method com/msxf/vopen/dto/jd/CommonResponse."<init>":(Lcom/msxf/vopen/dto/jd/CommonRequest;Lcom/msxf/vopen/constants/JDRespCodeEnum;Ljava/lang/String;)V
       721: areturn
      Exception table:
         from    to  target type
           102   112   115   Class java/lang/Exception
           291   304   307   Class com/msxf/eyas/cmc/CMCException
           354   366   369   Class com/msxf/eyas/cmc/CMCException
           474   486   489   Class com/msxf/uds/uas/exception/UASException
      LineNumberTable:
        line 144: 0
        line 145: 13
        line 146: 32
        line 148: 37
        line 149: 50
        line 152: 61
        line 153: 65
        line 154: 69
        line 155: 86
        line 158: 91
        line 162: 102
        line 166: 112
        line 163: 115
        line 164: 117
        line 165: 134
        line 169: 147
        line 170: 163
        line 171: 171
        line 172: 181
        line 173: 198
        line 175: 214
        line 176: 224
        line 179: 231
        line 182: 256
        line 183: 271
        line 184: 274
        line 187: 279
        line 188: 288
        line 190: 291
        line 194: 304
        line 191: 307
        line 192: 309
        line 193: 329
        line 197: 345
        line 199: 354
        line 203: 366
        line 200: 369
        line 201: 371
        line 202: 391
        line 206: 407
        line 208: 436
        line 209: 443
        line 210: 446
        line 214: 453
        line 216: 474
        line 223: 486
        line 217: 489
        line 218: 491
        line 219: 508
        line 220: 525
        line 222: 537
        line 226: 553
        line 229: 572
        line 230: 581
        line 231: 588
        line 235: 601
        line 237: 611
        line 239: 625
        line 240: 628
        line 242: 635
        line 243: 644
        line 244: 651
        line 245: 664
        line 249: 678
        line 252: 698
      LocalVariableTable:
        Start  Length  Slot  Name   Signature
          117      30     9     e   Ljava/lang/Exception;
          181      33    10 reqParam   Ljava/lang/String;
          309      36    17     e   Lcom/msxf/eyas/cmc/CMCException;
          371      36    18     e   Lcom/msxf/eyas/cmc/CMCException;
          288     155    15 userRegVo   Lcom/msxf/eyas/cmc/vo/user/UserMobileRegVo;
          291     152    16 loginResultVO   Lcom/msxf/eyas/cmc/vo/user/LoginResultVO;
          354      89    17 custInfo   Lcom/msxf/eyas/cmc/vo/cust/CustInfoVO;
          491      62    16     e   Lcom/msxf/uds/uas/exception/UASException;
          163     462     9 authCodeResp   Lcom/msxf/vopen/constants/CommonResult;
          224     401    10 creditAuthCodeResp   Lcom/msxf/vopen/dto/resp/CreditAuthCodeRespDTO;
          231     394    11 authCode   Ljava/lang/String;
          256     369    12 uniqueId   Ljava/lang/String;
          271     354    13 userInfo   Lcom/msxf/eyas/cmc/vo/user/UserBaseInfoVO;
          274     351    14 userId   Ljava/lang/Long;
          474     151    15 applyVo   Lcom/msxf/uds/uas/sdk/vo/ApplyVo;
          581      44    16 requestVo   Lcom/msxf/uds/uas/sdk/vo/ApplyQueryRequestVo;
          601      24    17 detailVo   Lcom/msxf/uds/uas/sdk/vo/ApplyQueryDetailVo;
          644      34     9 requestVo   Lcom/msxf/uds/uas/sdk/vo/ApplyQueryRequestVo;
          664      14    10 detailVo   Lcom/msxf/uds/uas/sdk/vo/ApplyQueryDetailVo;
            0     722     0  this   Lcom/msxf/vopen/service/biz/impl/jd/JDApplyServiceImpl;
            0     722     1 reqData   Lcom/msxf/vopen/dto/jd/CommonRequest;
           13     709     2   req   Lcom/msxf/vopen/dto/req/jd/CheckApplyReqDTO;
           37     685     3  user   Lcom/msxf/vopen/dto/req/jd/CheckApplyReqDTO$UserInfoDTO;
           50     672     4 apiCaller   Lcom/msxf/vopen/support/ApiCaller;
           61     661     5 channel   Lcom/msxf/vopen/entity/ChannelEntity;
           65     657     6 applyNo   Ljava/lang/String;
           69     653     7 feeRate   Ljava/lang/String;
           86     636     8 forJudge   Lcom/msxf/vopen/entity/ThirdRelationEntity;
      StackMapTable: number_of_entries = 14
        frame_type = 255 /* full_frame */
          offset_delta = 115
          locals = [ class com/msxf/vopen/service/biz/impl/jd/JDApplyServiceImpl, class com/msxf/vopen/dto/jd/CommonRequest, class com/msxf/vopen/dto/req/jd/CheckApplyReqDTO, class com/msxf/vopen/dto/req/jd/CheckApplyReqDTO$UserInfoDTO, class com/msxf/vopen/support/ApiCaller, class com/msxf/vopen/entity/ChannelEntity, class java/lang/String, class java/lang/String, class com/msxf/vopen/entity/ThirdRelationEntity ]
          stack = [ class java/lang/Exception ]
        frame_type = 31 /* same */
        frame_type = 252 /* append */
          offset_delta = 66
          locals = [ class com/msxf/vopen/constants/CommonResult ]
        frame_type = 255 /* full_frame */
          offset_delta = 92
          locals = [ class com/msxf/vopen/service/biz/impl/jd/JDApplyServiceImpl, class com/msxf/vopen/dto/jd/CommonRequest, class com/msxf/vopen/dto/req/jd/CheckApplyReqDTO, class com/msxf/vopen/dto/req/jd/CheckApplyReqDTO$UserInfoDTO, class com/msxf/vopen/support/ApiCaller, class com/msxf/vopen/entity/ChannelEntity, class java/lang/String, class java/lang/String, class com/msxf/vopen/entity/ThirdRelationEntity, class com/msxf/vopen/constants/CommonResult, class com/msxf/vopen/dto/resp/CreditAuthCodeRespDTO, class java/lang/String, class java/lang/String, class com/msxf/eyas/cmc/vo/user/UserBaseInfoVO, class java/lang/Long, class com/msxf/eyas/cmc/vo/user/UserMobileRegVo, class com/msxf/eyas/cmc/vo/user/LoginResultVO ]
          stack = [ class com/msxf/eyas/cmc/CMCException ]
        frame_type = 37 /* same */
        frame_type = 255 /* full_frame */
          offset_delta = 23
          locals = [ class com/msxf/vopen/service/biz/impl/jd/JDApplyServiceImpl, class com/msxf/vopen/dto/jd/CommonRequest, class com/msxf/vopen/dto/req/jd/CheckApplyReqDTO, class com/msxf/vopen/dto/req/jd/CheckApplyReqDTO$UserInfoDTO, class com/msxf/vopen/support/ApiCaller, class com/msxf/vopen/entity/ChannelEntity, class java/lang/String, class java/lang/String, class com/msxf/vopen/entity/ThirdRelationEntity, class com/msxf/vopen/constants/CommonResult, class com/msxf/vopen/dto/resp/CreditAuthCodeRespDTO, class java/lang/String, class java/lang/String, class com/msxf/eyas/cmc/vo/user/UserBaseInfoVO, class java/lang/Long, class com/msxf/eyas/cmc/vo/user/UserMobileRegVo, class com/msxf/eyas/cmc/vo/user/LoginResultVO, class com/msxf/eyas/cmc/vo/cust/CustInfoVO ]
          stack = [ class com/msxf/eyas/cmc/CMCException ]
        frame_type = 37 /* same */
        frame_type = 248 /* chop */
          offset_delta = 38
        frame_type = 6 /* same */
        frame_type = 255 /* full_frame */
          offset_delta = 35
          locals = [ class com/msxf/vopen/service/biz/impl/jd/JDApplyServiceImpl, class com/msxf/vopen/dto/jd/CommonRequest, class com/msxf/vopen/dto/req/jd/CheckApplyReqDTO, class com/msxf/vopen/dto/req/jd/CheckApplyReqDTO$UserInfoDTO, class com/msxf/vopen/support/ApiCaller, class com/msxf/vopen/entity/ChannelEntity, class java/lang/String, class java/lang/String, class com/msxf/vopen/entity/ThirdRelationEntity, class com/msxf/vopen/constants/CommonResult, class com/msxf/vopen/dto/resp/CreditAuthCodeRespDTO, class java/lang/String, class java/lang/String, class com/msxf/eyas/cmc/vo/user/UserBaseInfoVO, class java/lang/Long, class com/msxf/uds/uas/sdk/vo/ApplyVo ]
          stack = [ class com/msxf/uds/uas/exception/UASException ]
        frame_type = 252 /* append */
          offset_delta = 47
          locals = [ class com/msxf/uds/uas/exception/UASException ]
        frame_type = 250 /* chop */
          offset_delta = 15
        frame_type = 255 /* full_frame */
          offset_delta = 74
          locals = [ class com/msxf/vopen/service/biz/impl/jd/JDApplyServiceImpl, class com/msxf/vopen/dto/jd/CommonRequest, class com/msxf/vopen/dto/req/jd/CheckApplyReqDTO, class com/msxf/vopen/dto/req/jd/CheckApplyReqDTO$UserInfoDTO, class com/msxf/vopen/support/ApiCaller, class com/msxf/vopen/entity/ChannelEntity, class java/lang/String, class java/lang/String, class com/msxf/vopen/entity/ThirdRelationEntity ]
          stack = []
        frame_type = 49 /* same */
    Exceptions:
      throws java.lang.Exception

  public void uploadJDUserOCRInfo(java.lang.String, java.lang.String) throws java.lang.Exception;
    descriptor: (Ljava/lang/String;Ljava/lang/String;)V
    flags: ACC_PUBLIC
    Code:
      stack=6, locals=18, args_size=3
         0: aload_0
         1: getfield      #14                 // Field appBaseService:Lcom/msxf/vopen/service/AppBaseService;
         4: ldc           #9                  // String jd
         6: invokevirtual #15                 // Method com/msxf/vopen/service/AppBaseService.getChannelInfo:(Ljava/lang/String;)Lcom/msxf/vopen/entity/ChannelEntity;
         9: astore_3
        10: iconst_0
        11: istore        4
        13: iload         4
        15: iconst_3
        16: if_icmpge     376
        19: iload         4
        21: iconst_1
        22: iadd
        23: istore        5
        25: aconst_null
        26: astore        6
        28: new           #139                // class java/lang/StringBuilder
        31: dup
        32: invokespecial #140                // Method java/lang/StringBuilder."<init>":()V
        35: ldc_w         #339                // String /upload/crpl_msjr/ocr/
        38: invokevirtual #142                // Method java/lang/StringBuilder.append:(Ljava/lang/String;)Ljava/lang/StringBuilder;
        41: aload_1
        42: invokevirtual #142                // Method java/lang/StringBuilder.append:(Ljava/lang/String;)Ljava/lang/StringBuilder;
        45: ldc_w         #277                // String /
        48: invokevirtual #142                // Method java/lang/StringBuilder.append:(Ljava/lang/String;)Ljava/lang/StringBuilder;
        51: iload         5
        53: invokevirtual #340                // Method java/lang/StringBuilder.append:(I)Ljava/lang/StringBuilder;
        56: ldc_w         #341                // String .txt
        59: invokevirtual #142                // Method java/lang/StringBuilder.append:(Ljava/lang/String;)Ljava/lang/StringBuilder;
        62: invokevirtual #144                // Method java/lang/StringBuilder.toString:()Ljava/lang/String;
        65: astore        7
        67: aload_0
        68: getfield      #342                // Field host:Ljava/lang/String;
        71: aload_0
        72: getfield      #343                // Field port:Ljava/lang/Integer;
        75: invokevirtual #97                 // Method java/lang/Integer.intValue:()I
        78: aload_0
        79: getfield      #344                // Field username:Ljava/lang/String;
        82: aconst_null
        83: aload         7
        85: aload_0
        86: getfield      #345                // Field secret:Ljava/lang/String;
        89: invokestatic  #346                // Method com/msxf/vopen/util/FtpUtil.downloadViaSFTP:(Ljava/lang/String;ILjava/lang/String;Ljava/lang/String;Ljava/lang/String;Ljava/lang/String;)Ljava/io/InputStream;
        92: astore        6
        94: aload         6
        96: ldc_w         #347                // String UTF-8
        99: invokestatic  #348                // Method org/apache/commons/io/Charsets.toCharset:(Ljava/lang/String;)Ljava/nio/charset/Charset;
       102: invokestatic  #349                // Method org/apache/commons/io/IOUtils.toString:(Ljava/io/InputStream;Ljava/nio/charset/Charset;)Ljava/lang/String;
       105: astore        8
       107: aload         8
       109: invokestatic  #201                // Method org/apache/commons/lang3/StringUtils.isEmpty:(Ljava/lang/CharSequence;)Z
       112: ifeq          132
       115: new           #350                // class com/msxf/vopen/exception/JdOcrException
       118: dup
       119: getstatic     #351                // Field com/msxf/vopen/constants/CodeEnum.OCR_EXCEPTION:Lcom/msxf/vopen/constants/CodeEnum;
       122: invokevirtual #352                // Method com/msxf/vopen/constants/CodeEnum.getCode:()I
       125: ldc_w         #353                // String 京东OCR文件流为空!
       128: invokespecial #354                // Method com/msxf/vopen/exception/JdOcrException."<init>":(ILjava/lang/String;)V
       131: athrow
       132: aload         8
       134: aload_3
       135: invokevirtual #355                // Method com/msxf/vopen/entity/ChannelEntity.getSecretKey:()Ljava/lang/String;
       138: invokestatic  #356                // Method com/msxf/vopen/util/jd/DESUtil.decrypt2Byte:(Ljava/lang/String;Ljava/lang/String;)[B
       141: astore        9
       143: new           #357                // class java/io/ByteArrayInputStream
       146: dup
       147: aload         9
       149: invokespecial #358                // Method java/io/ByteArrayInputStream."<init>":([B)V
       152: astore        10
       154: lconst_0
       155: lstore        11
       157: aload_0
       158: getfield      #359                // Field ifsService:Lcom/msxf/eyas/ifs/IFSService;
       161: ldc_w         #360                // String 141001
       164: aload_2
       165: aload_0
       166: iload         5
       168: invokespecial #361                // Method parseOCRCategory:(I)Ljava/lang/String;
       171: ldc_w         #362                // String jpg
       174: aload         10
       176: invokeinterface #363,  6          // InterfaceMethod com/msxf/eyas/ifs/IFSService.upload:(Ljava/lang/String;Ljava/lang/String;Ljava/lang/String;Ljava/lang/String;Ljava/io/InputStream;)Ljava/lang/Long;
       181: invokevirtual #364                // Method java/lang/Long.longValue:()J
       184: lstore        11
       186: getstatic     #25                 // Field logger:Lorg/slf4j/Logger;
       189: ldc_w         #365                // String 上传京东用户OCR信息成功,文件id:{}
       192: lload         11
       194: invokestatic  #366                // Method java/lang/Long.valueOf:(J)Ljava/lang/Long;
       197: invokeinterface #367,  3          // InterfaceMethod org/slf4j/Logger.info:(Ljava/lang/String;Ljava/lang/Object;)V
       202: new           #207                // class java/util/ArrayList
       205: dup
       206: invokespecial #208                // Method java/util/ArrayList."<init>":()V
       209: astore        13
       211: aload         13
       213: lload         11
       215: invokestatic  #368                // Method java/lang/String.valueOf:(J)Ljava/lang/String;
       218: invokestatic  #205                // Method java/lang/Integer.valueOf:(Ljava/lang/String;)Ljava/lang/Integer;
       221: invokeinterface #223,  2          // InterfaceMethod java/util/List.add:(Ljava/lang/Object;)Z
       226: pop
       227: new           #207                // class java/util/ArrayList
       230: dup
       231: invokespecial #208                // Method java/util/ArrayList."<init>":()V
       234: astore        14
       236: aconst_null
       237: astore        15
       239: iload         5
       241: tableswitch   { // 1 to 3
                       1: 268
                       2: 279
                       3: 290
                 default: 301
            }
       268: getstatic     #369                // Field com/msxf/vopen/constants/IFSEnum.F:Lcom/msxf/vopen/constants/IFSEnum;
       271: invokevirtual #370                // Method com/msxf/vopen/constants/IFSEnum.name:()Ljava/lang/String;
       274: astore        15
       276: goto          315
       279: getstatic     #371                // Field com/msxf/vopen/constants/IFSEnum.R:Lcom/msxf/vopen/constants/IFSEnum;
       282: invokevirtual #370                // Method com/msxf/vopen/constants/IFSEnum.name:()Ljava/lang/String;
       285: astore        15
       287: goto          315
       290: getstatic     #372                // Field com/msxf/vopen/constants/IFSEnum.P:Lcom/msxf/vopen/constants/IFSEnum;
       293: invokevirtual #370                // Method com/msxf/vopen/constants/IFSEnum.name:()Ljava/lang/String;
       296: astore        15
       298: goto          315
       301: aload         6
       303: ifnull        311
       306: aload         6
       308: invokevirtual #373                // Method java/io/InputStream.close:()V
       311: invokestatic  #374                // Method com/msxf/vopen/util/FtpUtil.logoutViaSFTP:()V
       314: return
       315: aload         14
       317: aload         15
       319: invokeinterface #223,  2          // InterfaceMethod java/util/List.add:(Ljava/lang/Object;)Z
       324: pop
       325: aload_0
       326: getfield      #359                // Field ifsService:Lcom/msxf/eyas/ifs/IFSService;
       329: ldc_w         #360                // String 141001
       332: aload_2
       333: aload         13
       335: aload         14
       337: invokeinterface #375,  5          // InterfaceMethod com/msxf/eyas/ifs/IFSService.link:(Ljava/lang/String;Ljava/lang/String;Ljava/util/List;Ljava/util/List;)V
       342: aload         6
       344: ifnull        370
       347: aload         6
       349: invokevirtual #373                // Method java/io/InputStream.close:()V
       352: goto          370
       355: astore        16
       357: aload         6
       359: ifnull        367
       362: aload         6
       364: invokevirtual #373                // Method java/io/InputStream.close:()V
       367: aload         16
       369: athrow
       370: iinc          4, 1
       373: goto          13
       376: invokestatic  #374                // Method com/msxf/vopen/util/FtpUtil.logoutViaSFTP:()V
       379: goto          390
       382: astore        17
       384: invokestatic  #374                // Method com/msxf/vopen/util/FtpUtil.logoutViaSFTP:()V
       387: aload         17
       389: athrow
       390: return
      Exception table:
         from    to  target type
            28   301   355   any
           315   342   355   any
           355   357   355   any
             0   311   382   any
           315   376   382   any
           382   384   382   any
      LineNumberTable:
        line 483: 0
        line 484: 10
        line 486: 19
        line 487: 25
        line 490: 28
        line 491: 67
        line 493: 94
        line 494: 107
        line 495: 115
        line 498: 132
        line 499: 143
        line 501: 154
        line 503: 157
        line 504: 186
        line 506: 202
        line 507: 211
        line 509: 227
        line 510: 236
        line 511: 239
        line 513: 268
        line 514: 276
        line 516: 279
        line 517: 287
        line 519: 290
        line 520: 298
        line 529: 301
        line 530: 306
        line 535: 311
        line 522: 314
        line 524: 315
        line 526: 325
        line 529: 342
        line 530: 347
        line 529: 355
        line 530: 362
        line 484: 370
        line 535: 376
        line 536: 379
        line 535: 382
        line 537: 390
      LocalVariableTable:
        Start  Length  Slot  Name   Signature
           67     275     7 remoteUrl   Ljava/lang/String;
          107     235     8 content   Ljava/lang/String;
          143     199     9 imgBytes   [B
          154     188    10 imgStream   Ljava/io/InputStream;
          157     185    11 fileId   J
          211     131    13 fileIdList   Ljava/util/List;
          236     106    14 fileCategoryList   Ljava/util/List;
          239     103    15 fileCategory   Ljava/lang/String;
           25     345     5     j   I
           28     342     6    is   Ljava/io/InputStream;
           13     363     4     i   I
           10     366     3 entity   Lcom/msxf/vopen/entity/ChannelEntity;
            0     391     0  this   Lcom/msxf/vopen/service/biz/impl/jd/JDApplyServiceImpl;
            0     391     1 userId   Ljava/lang/String;
            0     391     2 applyNo   Ljava/lang/String;
      LocalVariableTypeTable:
        Start  Length  Slot  Name   Signature
          211     131    13 fileIdList   Ljava/util/List<Ljava/lang/Integer;>;
          236     106    14 fileCategoryList   Ljava/util/List<Ljava/lang/String;>;
      StackMapTable: number_of_entries = 14
        frame_type = 253 /* append */
          offset_delta = 13
          locals = [ class com/msxf/vopen/entity/ChannelEntity, int ]
        frame_type = 255 /* full_frame */
          offset_delta = 118
          locals = [ class com/msxf/vopen/service/biz/impl/jd/JDApplyServiceImpl, class java/lang/String, class java/lang/String, class com/msxf/vopen/entity/ChannelEntity, int, int, class java/io/InputStream, class java/lang/String, class java/lang/String ]
          stack = []
        frame_type = 255 /* full_frame */
          offset_delta = 135
          locals = [ class com/msxf/vopen/service/biz/impl/jd/JDApplyServiceImpl, class java/lang/String, class java/lang/String, class com/msxf/vopen/entity/ChannelEntity, int, int, class java/io/InputStream, class java/lang/String, class java/lang/String, class "[B", class java/io/InputStream, long, class java/util/List, class java/util/List, class java/lang/String ]
          stack = []
        frame_type = 10 /* same */
        frame_type = 10 /* same */
        frame_type = 10 /* same */
        frame_type = 9 /* same */
        frame_type = 3 /* same */
        frame_type = 255 /* full_frame */
          offset_delta = 39
          locals = [ class com/msxf/vopen/service/biz/impl/jd/JDApplyServiceImpl, class java/lang/String, class java/lang/String, class com/msxf/vopen/entity/ChannelEntity, int, int, class java/io/InputStream ]
          stack = [ class java/lang/Throwable ]
        frame_type = 255 /* full_frame */
          offset_delta = 11
          locals = [ class com/msxf/vopen/service/biz/impl/jd/JDApplyServiceImpl, class java/lang/String, class java/lang/String, class com/msxf/vopen/entity/ChannelEntity, int, int, class java/io/InputStream, top, top, top, top, top, top, top, top, top, class java/lang/Throwable ]
          stack = []
        frame_type = 255 /* full_frame */
          offset_delta = 2
          locals = [ class com/msxf/vopen/service/biz/impl/jd/JDApplyServiceImpl, class java/lang/String, class java/lang/String, class com/msxf/vopen/entity/ChannelEntity, int ]
          stack = []
        frame_type = 249 /* chop */
          offset_delta = 5
        frame_type = 69 /* same_locals_1_stack_item */
          stack = [ class java/lang/Throwable ]
        frame_type = 7 /* same */
    Exceptions:
      throws java.lang.Exception

  public com.msxf.vopen.dto.jd.CommonResponse notifyOCResult(com.msxf.vopen.dto.jd.CommonRequest) throws java.lang.Exception;
    descriptor: (Lcom/msxf/vopen/dto/jd/CommonRequest;)Lcom/msxf/vopen/dto/jd/CommonResponse;
    flags: ACC_PUBLIC
    Code:
      stack=4, locals=4, args_size=2
         0: aload_1
         1: invokevirtual #3                  // Method com/msxf/vopen/dto/jd/CommonRequest.getRequestData:()Ljava/lang/String;
         4: ldc_w         #379                // class com/msxf/vopen/dto/req/jd/NotifyIOCRReqDTO
         7: invokestatic  #5                  // Method com/alibaba/fastjson/JSONObject.parseObject:(Ljava/lang/String;Ljava/lang/Class;)Ljava/lang/Object;
        10: checkcast     #379                // class com/msxf/vopen/dto/req/jd/NotifyIOCRReqDTO
        13: astore_2
        14: getstatic     #25                 // Field logger:Lorg/slf4j/Logger;
        17: ldc_w         #380                // String 京东OCR请求参数:{}
        20: aload_2
        21: invokeinterface #381,  3          // InterfaceMethod org/slf4j/Logger.warn:(Ljava/lang/String;Ljava/lang/Object;)V
        26: aload_0
        27: getfield      #17                 // Field jdUserDao:Lcom/msxf/vopen/repository/ThirdRelationRepository;
        30: ldc_w         #382                // String JD
        33: aload_2
        34: invokevirtual #383                // Method com/msxf/vopen/dto/req/jd/NotifyIOCRReqDTO.getUserId:()Ljava/lang/String;
        37: invokeinterface #384,  3          // InterfaceMethod com/msxf/vopen/repository/ThirdRelationRepository.findByThirdUserId:(Ljava/lang/String;Ljava/lang/String;)Lcom/msxf/vopen/entity/ThirdRelationEntity;
        42: astore_3
        43: getstatic     #25                 // Field logger:Lorg/slf4j/Logger;
        46: ldc_w         #385                // String 京东OCR请求的第三方用信息{}
        49: aload_3
        50: invokeinterface #381,  3          // InterfaceMethod org/slf4j/Logger.warn:(Ljava/lang/String;Ljava/lang/Object;)V
        55: aload_0
        56: getfield      #87                 // Field jdNotifyService:Lcom/msxf/vopen/service/biz/jd/JDNotifyService;
        59: aload_2
        60: invokevirtual #383                // Method com/msxf/vopen/dto/req/jd/NotifyIOCRReqDTO.getUserId:()Ljava/lang/String;
        63: aload_3
        64: invokevirtual #92                 // Method com/msxf/vopen/entity/ThirdRelationEntity.getApplyNo:()Ljava/lang/String;
        67: invokeinterface #386,  3          // InterfaceMethod com/msxf/vopen/service/biz/jd/JDNotifyService.uploadJDUserOCRInfo:(Ljava/lang/String;Ljava/lang/String;)V
        72: new           #29                 // class com/msxf/vopen/dto/jd/CommonResponse
        75: dup
        76: getstatic     #100                // Field com/msxf/vopen/constants/JDRespCodeEnum.SUCCESS:Lcom/msxf/vopen/constants/JDRespCodeEnum;
        79: getstatic     #100                // Field com/msxf/vopen/constants/JDRespCodeEnum.SUCCESS:Lcom/msxf/vopen/constants/JDRespCodeEnum;
        82: invokevirtual #387                // Method com/msxf/vopen/constants/JDRespCodeEnum.getMessage:()Ljava/lang/String;
        85: invokespecial #32                 // Method com/msxf/vopen/dto/jd/CommonResponse."<init>":(Lcom/msxf/vopen/constants/JDRespCodeEnum;Ljava/lang/String;)V
        88: areturn
      LineNumberTable:
        line 554: 0
        line 555: 14
        line 556: 26
        line 557: 43
        line 558: 55
        line 559: 72
      LocalVariableTable:
        Start  Length  Slot  Name   Signature
            0      89     0  this   Lcom/msxf/vopen/service/biz/impl/jd/JDApplyServiceImpl;
            0      89     1   req   Lcom/msxf/vopen/dto/jd/CommonRequest;
           14      75     2 notifyReq   Lcom/msxf/vopen/dto/req/jd/NotifyIOCRReqDTO;
           43      46     3 entity   Lcom/msxf/vopen/entity/ThirdRelationEntity;
    Exceptions:
      throws java.lang.Exception

  static {};
    descriptor: ()V
    flags: ACC_STATIC
    Code:
      stack=1, locals=0, args_size=0
         0: ldc_w         #388                // class com/msxf/vopen/service/biz/impl/jd/JDApplyServiceImpl
         3: invokestatic  #389                // Method org/slf4j/LoggerFactory.getLogger:(Ljava/lang/Class;)Lorg/slf4j/Logger;
         6: putstatic     #25                 // Field logger:Lorg/slf4j/Logger;
         9: return
      LineNumberTable:
        line 77: 0
}
SourceFile: "JDApplyServiceImpl.java"
RuntimeVisibleAnnotations:
  0: #618()
InnerClasses:
     public static #487= #486 of #4; //UserInfoDTO=class com/msxf/vopen/dto/req/jd/CheckApplyReqDTO$UserInfoDTO of class com/msxf/vopen/dto/req/jd/CheckApplyReqDTO
     public static #529= #121 of #103; //ProductInfoDTO=class com/msxf/vopen/dto/resp/jd/CheckApplyRespDTO$ProductInfoDTO of class com/msxf/vopen/dto/resp/jd/CheckApplyRespDTO
     public static #539= #213 of #486; //emergInfoDTO=class com/msxf/vopen/dto/req/jd/CheckApplyReqDTO$UserInfoDTO$emergInfoDTO of class com/msxf/vopen/dto/req/jd/CheckApplyReqDTO$UserInfoDTO
